{"v":"5.12.1","fr":60,"ip":0,"op":124,"w":430,"h":430,"nm":"wired-lineal-1780-medal-first-place","ddd":0,"assets":[{"id":"comp_1","nm":"precomp-1","fr":60,"layers":[{"ddd":0,"ind":1,"ty":4,"nm":"Shape Layer 1","sr":1,"ks":{"o":{"a":0,"k":100,"ix":11},"r":{"a":0,"k":0,"ix":10},"p":{"a":0,"k":[215,214.25,0],"ix":2,"l":2},"a":{"a":0,"k":[0,0,0],"ix":1,"l":2},"s":{"a":0,"k":[100,100,100],"ix":6,"l":2}},"ao":0,"shapes":[{"ty":"gr","it":[{"ind":0,"ty":"sh","ix":1,"ks":{"a":1,"k":[{"i":{"x":0.833,"y":0.833},"o":{"x":0.167,"y":0.167},"t":24,"s":[{"i":[[0,0],[0,0]],"o":[[0,0],[0,0]],"v":[[-229.75,-160],[-144,-159.5]],"c":false}]},{"i":{"x":0.833,"y":0.833},"o":{"x":0.167,"y":0.167},"t":34,"s":[{"i":[[0,0],[0,0]],"o":[[0,0],[0,0]],"v":[[-143.25,-160],[-57.5,-159.5]],"c":false}]},{"i":{"x":0.833,"y":0.833},"o":{"x":0.167,"y":0.167},"t":38,"s":[{"i":[[0,0],[0,0]],"o":[[0,0],[0,0]],"v":[[-138.25,-160],[-52.5,-159.5]],"c":false}]},{"i":{"x":0.833,"y":0.833},"o":{"x":0.167,"y":0.167},"t":42,"s":[{"i":[[0,0],[0,0]],"o":[[0,0],[0,0]],"v":[[-133.5,-160],[-47.75,-159.5]],"c":false}]},{"t":46,"s":[{"i":[[0,0],[0,0]],"o":[[0,0],[0,0]],"v":[[-128.5,-160],[-42.75,-159.5]],"c":false}]}],"ix":2},"nm":"Path 1","mn":"ADBE Vector Shape - Group","hd":false},{"ty":"st","c":{"a":0,"k":[0.071,0.075,0.192,1],"ix":3,"x":"var $bm_rt;\n$bm_rt = comp('wired-lineal-1780-medal-first-place').layer('control').effect('primary')('Color');"},"o":{"a":0,"k":100,"ix":4},"w":{"a":0,"k":7,"ix":5,"x":"var $bm_rt;\n$bm_rt = $bm_mul($bm_div(value, 2), comp('wired-lineal-1780-medal-first-place').layer('control').effect('stroke')('Menu'));"},"lc":2,"lj":2,"bm":0,"nm":".primary","mn":"ADBE Vector Graphic - Stroke","hd":false,"cl":"primary"},{"ty":"tr","p":{"a":0,"k":[171.75,0],"ix":2},"a":{"a":0,"k":[0,0],"ix":1},"s":{"a":0,"k":[100,100],"ix":3},"r":{"a":0,"k":0,"ix":6},"o":{"a":0,"k":100,"ix":7},"sk":{"a":0,"k":0,"ix":4},"sa":{"a":0,"k":0,"ix":5},"nm":"Transform"}],"nm":"Shape 2","np":3,"cix":2,"bm":0,"ix":1,"mn":"ADBE Vector Group","hd":false},{"ty":"gr","it":[{"ind":0,"ty":"sh","ix":1,"ks":{"a":1,"k":[{"i":{"x":0.833,"y":0.833},"o":{"x":0.167,"y":0.167},"t":24,"s":[{"i":[[0,0],[0,0]],"o":[[0,0],[0,0]],"v":[[-58.5,-160],[27.25,-159.5]],"c":false}]},{"i":{"x":0.833,"y":0.833},"o":{"x":0.167,"y":0.167},"t":34,"s":[{"i":[[0,0],[0,0]],"o":[[0,0],[0,0]],"v":[[-113.75,-160],[-28,-159.5]],"c":false}]},{"i":{"x":0.833,"y":0.833},"o":{"x":0.167,"y":0.167},"t":38,"s":[{"i":[[0,0],[0,0]],"o":[[0,0],[0,0]],"v":[[-118.75,-160],[-33,-159.5]],"c":false}]},{"i":{"x":0.833,"y":0.833},"o":{"x":0.167,"y":0.167},"t":42,"s":[{"i":[[0,0],[0,0]],"o":[[0,0],[0,0]],"v":[[-123.25,-160],[-37.5,-159.5]],"c":false}]},{"t":46,"s":[{"i":[[0,0],[0,0]],"o":[[0,0],[0,0]],"v":[[-128.5,-160],[-42.75,-159.5]],"c":false}]}],"ix":2},"nm":"Path 1","mn":"ADBE Vector Shape - Group","hd":false},{"ty":"st","c":{"a":0,"k":[0.071,0.075,0.192,1],"ix":3,"x":"var $bm_rt;\n$bm_rt = comp('wired-lineal-1780-medal-first-place').layer('control').effect('primary')('Color');"},"o":{"a":0,"k":100,"ix":4},"w":{"a":0,"k":7,"ix":5,"x":"var $bm_rt;\n$bm_rt = $bm_mul($bm_div(value, 2), comp('wired-lineal-1780-medal-first-place').layer('control').effect('stroke')('Menu'));"},"lc":2,"lj":2,"bm":0,"nm":".primary","mn":"ADBE Vector Graphic - Stroke","hd":false,"cl":"primary"},{"ty":"tr","p":{"a":0,"k":[0,0],"ix":2},"a":{"a":0,"k":[0,0],"ix":1},"s":{"a":0,"k":[100,100],"ix":3},"r":{"a":0,"k":0,"ix":6},"o":{"a":0,"k":100,"ix":7},"sk":{"a":0,"k":0,"ix":4},"sa":{"a":0,"k":0,"ix":5},"nm":"Transform"}],"nm":"Shape 1","np":3,"cix":2,"bm":0,"ix":2,"mn":"ADBE Vector Group","hd":false}],"ip":0,"op":844,"st":0,"ct":1,"bm":0},{"ddd":0,"ind":2,"ty":4,"nm":"Ribbon 3","sr":1,"ks":{"o":{"a":0,"k":100,"ix":11},"r":{"a":0,"k":0,"ix":10},"p":{"a":0,"k":[171.97,54.881,0],"ix":2,"l":2},"a":{"a":0,"k":[206.97,89.881,0],"ix":1,"l":2},"s":{"a":1,"k":[{"i":{"x":[0.667,0.667,0.667],"y":[1,1,1]},"o":{"x":[0.333,0.333,0.333],"y":[0,0,0]},"t":55,"s":[100,100,100]},{"i":{"x":[0.667,0.667,0.667],"y":[1,1,1]},"o":{"x":[0.333,0.333,0.333],"y":[0,0,0]},"t":70,"s":[100,93,100]},{"t":84,"s":[100,100,100]}],"ix":6,"l":2}},"ao":0,"shapes":[{"ty":"gr","it":[{"ind":0,"ty":"sh","ix":1,"ks":{"a":1,"k":[{"i":{"x":0.833,"y":0.833},"o":{"x":0.167,"y":0.167},"t":24,"s":[{"i":[[0,0],[0.362,-8.3]],"o":[[0,0],[0,0]],"v":[[29.126,-103.611],[30.008,-90.695]],"c":false}]},{"i":{"x":0.833,"y":0.833},"o":{"x":0.167,"y":0.167},"t":34,"s":[{"i":[[0,0],[-15.71,-83.834]],"o":[[0,0],[0,0]],"v":[[-27.005,-103.615],[-0.42,26.338]],"c":false}]},{"i":{"x":0.833,"y":0.833},"o":{"x":0.167,"y":0.167},"t":38,"s":[{"i":[[0,0],[-6.374,-84.412]],"o":[[0,0],[0,0]],"v":[[-31.466,-103.615],[-6.711,103.949]],"c":false}]},{"i":{"x":0.833,"y":0.833},"o":{"x":0.167,"y":0.167},"t":42,"s":[{"i":[[0,0],[2.961,-84.991]],"o":[[0,0],[0,0]],"v":[[-35.927,-103.615],[8.409,143.495]],"c":false}]},{"i":{"x":0.833,"y":0.833},"o":{"x":0.167,"y":0.167},"t":46,"s":[{"i":[[0,0],[-13.194,-77.338]],"o":[[0,0],[0,0]],"v":[[-41.544,-103.615],[39.844,144.116]],"c":false}]},{"i":{"x":0.833,"y":0.833},"o":{"x":0.167,"y":0.167},"t":51,"s":[{"i":[[0,0],[-33.387,-67.772]],"o":[[0,0],[0,0]],"v":[[-41.874,-103.615],[68.136,124.671]],"c":false}]},{"i":{"x":0.833,"y":0.833},"o":{"x":0.167,"y":0.167},"t":55,"s":[{"i":[[0,0],[-40.417,-63.829]],"o":[[0,0],[0,0]],"v":[[-41.874,-103.615],[64.971,113.602]],"c":false}]},{"i":{"x":0.667,"y":1},"o":{"x":0.167,"y":0.167},"t":62,"s":[{"i":[[0,0],[-38.711,-64.878]],"o":[[0,0],[0,0]],"v":[[-41.874,-103.615],[45.791,89.995]],"c":false}]},{"i":{"x":0.667,"y":1},"o":{"x":0.333,"y":0},"t":70,"s":[{"i":[[0,0],[-23.864,-70.579]],"o":[[0,0],[0,0]],"v":[[-41.874,-103.615],[29.036,94.468]],"c":false}]},{"t":84,"s":[{"i":[[0,0],[-27.916,-69.077]],"o":[[0,0],[0,0]],"v":[[-41.874,-103.615],[41.874,103.615]],"c":false}]}],"ix":2},"nm":"Path 1","mn":"ADBE Vector Shape - Group","hd":false},{"ty":"st","c":{"a":0,"k":[0.071,0.075,0.192,1],"ix":3,"x":"var $bm_rt;\n$bm_rt = comp('wired-lineal-1780-medal-first-place').layer('control').effect('primary')('Color');"},"o":{"a":0,"k":100,"ix":4},"w":{"a":0,"k":7,"ix":5,"x":"var $bm_rt;\n$bm_rt = $bm_mul($bm_div(value, 2), comp('wired-lineal-1780-medal-first-place').layer('control').effect('stroke')('Menu'));"},"lc":2,"lj":2,"bm":0,"nm":".primary","mn":"ADBE Vector Graphic - Stroke","hd":false,"cl":"primary"},{"ty":"tr","p":{"a":0,"k":[206.13,193.496],"ix":2},"a":{"a":0,"k":[0,0],"ix":1},"s":{"a":0,"k":[100,100],"ix":3},"r":{"a":0,"k":0,"ix":6},"o":{"a":0,"k":100,"ix":7},"sk":{"a":0,"k":0,"ix":4},"sa":{"a":0,"k":0,"ix":5},"nm":"Transform"}],"nm":"Group 1","np":2,"cix":2,"bm":0,"ix":1,"mn":"ADBE Vector Group","hd":false},{"ty":"gr","it":[{"ty":"gr","it":[{"ind":0,"ty":"sh","ix":1,"ks":{"a":1,"k":[{"i":{"x":0.833,"y":0.833},"o":{"x":0.167,"y":0.167},"t":24,"s":[{"i":[[0,0],[-0.009,-5.719],[-22.865,0.653],[0,0]],"o":[[0,0],[23.505,0.086],[0.5,-9.072],[0,0]],"v":[[-14.903,-106.742],[-14.961,-91.158],[70.53,-91.055],[70.494,-106.742]],"c":false}]},{"i":{"x":0.833,"y":0.833},"o":{"x":0.167,"y":0.167},"t":34,"s":[{"i":[[0,0],[-15.951,-68.247],[-23.18,-5.712],[0,0]],"o":[[0,0],[23.627,6.602],[-14.187,-98.373],[0,0]],"v":[[-71.034,-106.746],[-46.019,20.12],[40.717,40.246],[14.363,-106.746]],"c":false}]},{"i":{"x":0.833,"y":0.833},"o":{"x":0.167,"y":0.167},"t":38,"s":[{"i":[[0,0],[-3.176,-75.002],[-22.444,-7.824],[0,0]],"o":[[0,0],[22.804,8.748],[-2.394,-101.218],[0,0]],"v":[[-75.495,-106.746],[-51.63,93.583],[32.469,121.623],[9.902,-106.746]],"c":false}]},{"i":{"x":0.833,"y":0.833},"o":{"x":0.167,"y":0.167},"t":42,"s":[{"i":[[0,0],[-0.065,-72.241],[-21.707,-9.936],[0,0]],"o":[[0,0],[21.98,10.894],[9.399,-104.062],[0,0]],"v":[[-79.955,-106.746],[-35.829,128.982],[45.631,164.936],[5.442,-106.746]],"c":false}]},{"i":{"x":0.833,"y":0.833},"o":{"x":0.167,"y":0.167},"t":46,"s":[{"i":[[0,0],[-13.77,-69.155],[-22.669,-5.394],[0,0]],"o":[[0,0],[23.112,6.26],[-10.465,-90.808],[0,0]],"v":[[-85.572,-106.746],[-3.099,137.562],[80.109,157.289],[-0.176,-106.746]],"c":false}]},{"i":{"x":0.833,"y":0.833},"o":{"x":0.167,"y":0.167},"t":51,"s":[{"i":[[0,0],[-30.901,-65.299],[-23.872,0.283],[0,0]],"o":[[0,0],[24.527,0.467],[-35.296,-74.241],[0,0]],"v":[[-85.903,-106.746],[26.809,128.067],[112.205,127.509],[-0.506,-106.746]],"c":false}]},{"i":{"x":0.833,"y":0.833},"o":{"x":0.167,"y":0.167},"t":55,"s":[{"i":[[0,0],[-37.681,-61.635],[-23.706,2.824],[0,0]],"o":[[0,0],[24.438,-2.149],[-43.004,-70.058],[0,0]],"v":[[-85.903,-106.746],[24.57,121.274],[109.42,111.622],[-0.506,-106.746]],"c":false}]},{"i":{"x":0.667,"y":1},"o":{"x":0.167,"y":0.167},"t":62,"s":[{"i":[[0,0],[-36.035,-62.612],[-23.772,2.195],[0,0]],"o":[[0,0],[24.486,-1.501],[-41.133,-71.173],[0,0]],"v":[[-85.903,-106.746],[5.118,96.615],[90.194,89.215],[-0.506,-106.746]],"c":false}]},{"i":{"x":0.667,"y":1},"o":{"x":0.333,"y":0},"t":70,"s":[{"i":[[0,0],[-23.082,-67.826],[-23.84,-1.258],[0,0]],"o":[[0,0],[24.446,2.048],[-26.422,-77.536],[0,0]],"v":[[-85.903,-106.746],[-12.627,95.239],[72.627,100.191],[-0.506,-106.746]],"c":false}]},{"t":84,"s":[{"i":[[0,0],[-26.976,-66.373],[-23.873,0.127],[0,0]],"o":[[0,0],[24.524,0.627],[-30.873,-75.873],[0,0]],"v":[[-85.903,-106.746],[0.506,106.746],[85.903,106.746],[-0.506,-106.746]],"c":false}]}],"ix":2},"nm":"Path 1","mn":"ADBE Vector Shape - Group","hd":false},{"ty":"st","c":{"a":0,"k":[0.071,0.075,0.192,1],"ix":3,"x":"var $bm_rt;\n$bm_rt = comp('wired-lineal-1780-medal-first-place').layer('control').effect('primary')('Color');"},"o":{"a":0,"k":100,"ix":4},"w":{"a":0,"k":7,"ix":5,"x":"var $bm_rt;\n$bm_rt = $bm_mul($bm_div(value, 2), comp('wired-lineal-1780-medal-first-place').layer('control').effect('stroke')('Menu'));"},"lc":2,"lj":2,"bm":0,"nm":".primary","mn":"ADBE Vector Graphic - Stroke","hd":false,"cl":"primary"},{"ty":"tr","p":{"a":0,"k":[206.97,196.627],"ix":2},"a":{"a":0,"k":[0,0],"ix":1},"s":{"a":0,"k":[100,100],"ix":3},"r":{"a":0,"k":0,"ix":6},"o":{"a":0,"k":100,"ix":7},"sk":{"a":0,"k":0,"ix":4},"sa":{"a":0,"k":0,"ix":5},"nm":"Transform"}],"nm":"Group 1","np":2,"cix":2,"bm":0,"ix":1,"mn":"ADBE Vector Group","hd":false},{"ty":"tr","p":{"a":0,"k":[293.03,196.627],"ix":2},"a":{"a":0,"k":[293.03,196.627],"ix":1},"s":{"a":0,"k":[100,100],"ix":3},"r":{"a":0,"k":0,"ix":6},"o":{"a":0,"k":100,"ix":7},"sk":{"a":0,"k":0,"ix":4},"sa":{"a":0,"k":0,"ix":5},"nm":"Transform"}],"nm":"Group 2","np":1,"cix":2,"bm":0,"ix":2,"mn":"ADBE Vector Group","hd":false},{"ty":"tm","s":{"a":0,"k":0,"ix":1},"e":{"a":0,"k":100,"ix":2},"o":{"a":0,"k":0,"ix":3},"m":1,"ix":3,"nm":"Trim Paths 1","mn":"ADBE Vector Filter - Trim","hd":false}],"ip":0,"op":844,"st":0,"ct":1,"bm":0},{"ddd":0,"ind":3,"ty":4,"nm":"Warstwa 1 fill 2","parent":2,"sr":1,"ks":{"o":{"a":0,"k":100,"ix":11},"r":{"a":0,"k":0,"ix":10},"p":{"a":0,"k":[178.147,182.718,0],"ix":2,"l":2},"a":{"a":0,"k":[0,0,0],"ix":1,"l":2},"s":{"a":0,"k":[100,100,100],"ix":6,"l":2}},"ao":0,"shapes":[{"ty":"gr","it":[{"ind":0,"ty":"sh","ix":1,"ks":{"a":1,"k":[{"i":{"x":0.833,"y":0.833},"o":{"x":0.167,"y":0.167},"t":24,"s":[{"i":[[-1.212,-9.28],[-11.177,0.254],[0.965,5.646],[6.353,0]],"o":[[9.788,0.47],[-0.677,-7.496],[-4.04,0],[0.31,3.277]],"v":[[14.065,-77.688],[58.03,-77.972],[56.638,-93.364],[13.793,-93.245]],"c":true}]},{"i":{"x":0.833,"y":0.833},"o":{"x":0.167,"y":0.167},"t":34,"s":[{"i":[[-14.761,-61.616],[-11.508,-2.771],[2.179,5],[9.001,0]],"o":[[9.548,3.384],[-12.87,-75.932],[-3.234,0],[2.693,5.56]],"v":[[-16.886,34.148],[28.973,44.964],[1.33,-93.18],[-41.515,-93.061]],"c":true}]},{"i":{"x":0.833,"y":0.833},"o":{"x":0.167,"y":0.167},"t":38,"s":[{"i":[[-4.149,-54.994],[-12.028,-3.103],[1.961,4.502],[10.06,0]],"o":[[9.447,3.756],[-6.762,-82.065],[-2.911,0],[3.01,6.214]],"v":[[-21.248,107.526],[21.615,122.097],[-2.993,-93.206],[-45.838,-93.087]],"c":true}]},{"i":{"x":0.833,"y":0.833},"o":{"x":0.167,"y":0.167},"t":42,"s":[{"i":[[0.846,-57.872],[-12.548,-3.435],[1.744,4.003],[11.119,0]],"o":[[9.346,4.128],[2.952,-89.435],[-2.589,0],[3.327,6.868]],"v":[[-6.992,142.904],[36.152,161.467],[-8.172,-92.956],[-51.017,-92.837]],"c":true}]},{"i":{"x":0.833,"y":0.833},"o":{"x":0.167,"y":0.167},"t":46,"s":[{"i":[[-12.256,-58.846],[-13.002,-3.411],[1.527,3.505],[12.177,0]],"o":[[9.631,0.226],[-5.002,-55.161],[-2.266,0],[3.643,7.522]],"v":[[25.109,151.878],[69.105,163.694],[-14.172,-92.956],[-57.017,-92.837]],"c":true}]},{"i":{"x":0.833,"y":0.833},"o":{"x":0.167,"y":0.167},"t":51,"s":[{"i":[[-24.577,-46.473],[-12.3,0.067],[1.255,2.881],[13.501,0]],"o":[[9.547,0.226],[-28.979,-55.543],[-1.863,0],[4.039,8.339]],"v":[[55.931,142.255],[100.332,142.575],[-14.172,-92.956],[-57.017,-92.837]],"c":true}]},{"i":{"x":0.833,"y":0.833},"o":{"x":0.167,"y":0.167},"t":55,"s":[{"i":[[-26.321,-38.508],[-13.097,0.693],[1.038,2.383],[14.56,0]],"o":[[9.48,0.226],[-38.347,-58.807],[-1.541,0],[4.356,8.994]],"v":[[53.925,135.29],[98.2,131.339],[-14.172,-92.956],[-57.017,-92.837]],"c":true}]},{"i":{"x":0.833,"y":0.833},"o":{"x":0.167,"y":0.167},"t":62,"s":[{"i":[[-25.857,-40.518],[-13.425,0.07],[0.658,1.51],[16.413,0]],"o":[[9.361,0.226],[-38.193,-62.289],[-0.977,0],[4.911,10.138]],"v":[[33.336,109.266],[77.796,107.031],[-14.172,-92.956],[-57.017,-92.837]],"c":true}]},{"i":{"x":0.667,"y":1},"o":{"x":0.167,"y":0.167},"t":70,"s":[{"i":[[-15.683,-39.816],[-14.243,0.072],[0.223,0.513],[18.531,0]],"o":[[9.227,0.226],[-27.13,-67.623],[-0.332,0],[5.544,11.446]],"v":[[16.87,109.266],[60.413,110.35],[-14.172,-92.956],[-57.017,-92.837]],"c":true}]},{"t":84,"s":[{"i":[[-15.968,-40.524],[-14.664,0.073],[0,0],[19.62,0]],"o":[[9.157,0.226],[-28.289,-70.552],[0,0],[5.87,12.119]],"v":[[28.821,120.556],[72.142,120.834],[-14.172,-92.956],[-57.017,-92.837]],"c":true}]}],"ix":2},"nm":"Path 1","mn":"ADBE Vector Shape - Group","hd":false},{"ty":"fl","c":{"a":0,"k":[0.443,0.4,0.933,1],"ix":4,"x":"var $bm_rt;\n$bm_rt = comp('wired-lineal-1780-medal-first-place').layer('control').effect('quaternary')('Color');"},"o":{"a":0,"k":100,"ix":5},"r":1,"bm":0,"nm":".quaternary","mn":"ADBE Vector Graphic - Fill","hd":false,"cl":"quaternary"},{"ty":"tr","p":{"a":0,"k":[0,0],"ix":2},"a":{"a":0,"k":[0,0],"ix":1},"s":{"a":0,"k":[100,100],"ix":3},"r":{"a":0,"k":0,"ix":6},"o":{"a":0,"k":100,"ix":7},"sk":{"a":0,"k":0,"ix":4},"sa":{"a":0,"k":0,"ix":5},"nm":"Transform"}],"nm":"Group 1","np":2,"cix":2,"bm":0,"ix":1,"mn":"ADBE Vector Group","hd":false}],"ip":0,"op":844,"st":0,"ct":1,"bm":0},{"ddd":0,"ind":4,"ty":4,"nm":"Ribbon fill","parent":2,"sr":1,"ks":{"o":{"a":0,"k":100,"ix":11},"r":{"a":0,"k":0,"ix":10},"p":{"a":0,"k":[250,196.627,0],"ix":2,"l":2},"a":{"a":0,"k":[250,196.627,0],"ix":1,"l":2},"s":{"a":0,"k":[100,100,100],"ix":6,"l":2}},"ao":0,"shapes":[{"ty":"gr","it":[{"ind":0,"ty":"sh","ix":1,"ks":{"a":1,"k":[{"i":{"x":0.833,"y":0.833},"o":{"x":0.167,"y":0.167},"t":24,"s":[{"i":[[0,0],[-2.338,-67.869],[-27.14,-0.236],[0,0]],"o":[[0,0],[28.197,0.273],[0.61,-5.736],[0,0]],"v":[[-12.155,-107.859],[-12.792,-92.4],[70.42,-91.391],[70.492,-107.859]],"c":false}]},{"i":{"x":0.833,"y":0.833},"o":{"x":0.167,"y":0.167},"t":34,"s":[{"i":[[0,0],[7.928,-68.492],[-26.648,-5.533],[0,0]],"o":[[0,0],[29.404,8.105],[-17.148,-129.033],[0,0]],"v":[[-69.135,-104.989],[-43.124,19.768],[39.178,38.906],[13.762,-105.989]],"c":false}]},{"i":{"x":0.833,"y":0.833},"o":{"x":0.167,"y":0.167},"t":38,"s":[{"i":[[0,0],[12.034,-68.741],[-26.401,-2.562],[0,0]],"o":[[0,0],[28.376,3.668],[-9.022,-183.042],[0,0]],"v":[[-74.427,-105.341],[-50.493,93.638],[32.004,119.499],[10.97,-105.341]],"c":false}]},{"i":{"x":0.833,"y":0.833},"o":{"x":0.167,"y":0.167},"t":42,"s":[{"i":[[0,0],[16.141,-68.991],[-26.667,-2.845],[0,0]],"o":[[0,0],[28.782,3.988],[-6.722,-194.323],[0,0]],"v":[[-80.403,-105.746],[-34.861,130.114],[46.501,163.946],[4.994,-105.746]],"c":false}]},{"i":{"x":0.833,"y":0.833},"o":{"x":0.167,"y":0.167},"t":46,"s":[{"i":[[0,0],[-8.312,-78.192],[-26.933,-3.128],[0,0]],"o":[[0,0],[29.188,4.308],[-4.683,-71.378],[0,0]],"v":[[-85.903,-106.746],[-2.908,137.815],[79.713,156.251],[-0.506,-106.746]],"c":false}]},{"i":{"x":0.833,"y":0.833},"o":{"x":0.167,"y":0.167},"t":51,"s":[{"i":[[0,0],[-35.295,-73.901],[-26.684,-0.229],[0,0]],"o":[[0,0],[29.505,-2.237],[-36.299,-76.775],[0,0]],"v":[[-85.903,-106.746],[25.824,129.274],[112.579,128.648],[-0.506,-106.746]],"c":false}]},{"i":{"x":0.833,"y":0.833},"o":{"x":0.167,"y":0.167},"t":55,"s":[{"i":[[0,0],[-35.955,-68.767],[-28.788,4.281],[0,0]],"o":[[0,0],[29.896,-2.462],[-42.443,-72.84],[0,0]],"v":[[-85.903,-106.746],[25.384,121.335],[108.318,110.592],[-0.506,-106.746]],"c":false}]},{"i":{"x":0.833,"y":0.833},"o":{"x":0.167,"y":0.167},"t":62,"s":[{"i":[[0,0],[-37.098,-69.071],[-27.291,-0.306],[0,0]],"o":[[0,0],[24.524,0.627],[-43.916,-72.454],[0,0]],"v":[[-85.903,-106.746],[4.877,96.419],[92.571,90.509],[-0.506,-106.746]],"c":false}]},{"i":{"x":0.667,"y":1},"o":{"x":0.167,"y":0.167},"t":70,"s":[{"i":[[0,0],[-26.976,-66.373],[-24.373,-1.536],[0,0]],"o":[[0,0],[24.524,0.627],[-30.873,-75.873],[0,0]],"v":[[-85.903,-106.746],[-11.494,94.649],[72.403,99.488],[-0.506,-106.746]],"c":false}]},{"t":84,"s":[{"i":[[0,0],[-26.976,-66.373],[-23.873,0.127],[0,0]],"o":[[0,0],[24.524,0.627],[-30.873,-75.873],[0,0]],"v":[[-85.903,-106.746],[0.506,106.746],[85.903,106.746],[-0.506,-106.746]],"c":false}]}],"ix":2},"nm":"Path 1","mn":"ADBE Vector Shape - Group","hd":false},{"ty":"fl","c":{"a":0,"k":[0.922,0.902,0.937,1],"ix":4,"x":"var $bm_rt;\n$bm_rt = comp('wired-lineal-1780-medal-first-place').layer('control').effect('tertiary')('Color');"},"o":{"a":0,"k":100,"ix":5},"r":1,"bm":0,"nm":".tertiary","mn":"ADBE Vector Graphic - Fill","hd":false,"cl":"tertiary"},{"ty":"tr","p":{"a":0,"k":[206.97,196.627],"ix":2},"a":{"a":0,"k":[0,0],"ix":1},"s":{"a":0,"k":[100,100],"ix":3},"r":{"a":0,"k":0,"ix":6},"o":{"a":0,"k":100,"ix":7},"sk":{"a":0,"k":0,"ix":4},"sa":{"a":0,"k":0,"ix":5},"nm":"Transform"}],"nm":"Group 1","np":3,"cix":2,"bm":0,"ix":1,"mn":"ADBE Vector Group","hd":false}],"ip":0,"op":844,"st":0,"ct":1,"bm":0},{"ddd":0,"ind":5,"ty":4,"nm":"Ribbon 2","sr":1,"ks":{"o":{"a":0,"k":100,"ix":11},"r":{"a":0,"k":0,"ix":10},"p":{"a":0,"k":[258.03,54.881,0],"ix":2,"l":2},"a":{"a":0,"k":[293.03,89.881,0],"ix":1,"l":2},"s":{"a":1,"k":[{"i":{"x":[0.667,0.667,0.667],"y":[1,1,1]},"o":{"x":[0.333,0.333,0.333],"y":[0,0,0]},"t":55,"s":[100,100,100]},{"i":{"x":[0.667,0.667,0.667],"y":[1,1,1]},"o":{"x":[0.333,0.333,0.333],"y":[0,0,0]},"t":70,"s":[100,93,100]},{"t":84,"s":[100,100,100]}],"ix":6,"l":2}},"ao":0,"shapes":[{"ty":"gr","it":[{"ty":"gr","it":[{"ind":0,"ty":"sh","ix":1,"ks":{"a":1,"k":[{"i":{"x":0.833,"y":0.833},"o":{"x":0.167,"y":0.167},"t":24,"s":[{"i":[[0,0],[-0.01,-1.604],[8.575,3.586],[0,0]],"o":[[0,0],[-33.523,0.275],[0.886,-0.421],[0,0]],"v":[[-15.292,-106.662],[-15.019,-90.046],[-102.916,-89.706],[-101.682,-107.146]],"c":false}]},{"i":{"x":0.833,"y":0.833},"o":{"x":0.167,"y":0.167},"t":34,"s":[{"i":[[0,0],[89.062,-45.734],[4.184,8.3],[0,0]],"o":[[0,0],[-25.651,-21.584],[80.961,-60.477],[0,0]],"v":[[71.034,-106.746],[-66.592,69.607],[-131.686,14.332],[-14.363,-106.746]],"c":false}]},{"i":{"x":0.833,"y":0.833},"o":{"x":0.167,"y":0.167},"t":38,"s":[{"i":[[0,0],[69.33,-64.626],[5.356,7.459],[0,0]],"o":[[0,0],[-28.342,-17.133],[69.744,-71.43],[0,0]],"v":[[75.495,-106.746],[-68.052,134.354],[-140.051,90.386],[-9.902,-106.746]],"c":false}]},{"i":{"x":0.833,"y":0.833},"o":{"x":0.167,"y":0.167},"t":42,"s":[{"i":[[0,0],[62.463,-78.82],[6.527,6.618],[0,0]],"o":[[0,0],[-31.033,-12.683],[58.527,-82.382],[0,0]],"v":[[79.955,-106.746],[-46.911,161.633],[-121.057,130.755],[-5.442,-106.746]],"c":false}]},{"i":{"x":0.833,"y":0.833},"o":{"x":0.167,"y":0.167},"t":46,"s":[{"i":[[0,0],[38.298,-79.116],[3.626,3.677],[0,0]],"o":[[0,0],[-32.14,-6.993],[27.308,-57.988],[0,0]],"v":[[85.572,-106.746],[-7.877,153.008],[-89.667,134.853],[0.175,-106.746]],"c":false}]},{"i":{"x":0.833,"y":0.833},"o":{"x":0.167,"y":0.167},"t":51,"s":[{"i":[[0,0],[20.37,-76.874],[0,0],[0,0]],"o":[[0,0],[-33.524,0.119],[0,0],[0,0]],"v":[[85.903,-106.746],[25.005,126.763],[-60.391,126.743],[0.506,-106.746]],"c":false}]},{"i":{"x":0.833,"y":0.833},"o":{"x":0.167,"y":0.167},"t":55,"s":[{"i":[[0,0],[11.834,-76.304],[7.664,-0.416],[0,0]],"o":[[0,0],[-33.152,4.981],[7.164,-91.916],[0,0]],"v":[[85.903,-106.746],[22.802,109.421],[-61.694,121.789],[0.506,-106.746]],"c":false}]},{"i":{"x":0.667,"y":1},"o":{"x":0.167,"y":0.167},"t":62,"s":[{"i":[[0,0],[21.625,-70.249],[10.556,-0.286],[0,0]],"o":[[0,0],[-33.414,2.711],[24.056,-94.763],[0,0]],"v":[[85.903,-106.746],[6.057,96.684],[-79.086,103.267],[0.506,-106.746]],"c":false}]},{"i":{"x":0.667,"y":1},"o":{"x":0.333,"y":0},"t":70,"s":[{"i":[[0,0],[29.983,-67.109],[0,0],[0,0]],"o":[[0,0],[-33.497,-1.361],[0,0],[0,0]],"v":[[85.903,-106.746],[-4.846,103.24],[-90.159,99.451],[0.506,-106.746]],"c":false}]},{"t":84,"s":[{"i":[[0,0],[26.976,-68.373],[0,0],[0,0]],"o":[[0,0],[-33.524,0.127],[0,0],[0,0]],"v":[[85.903,-106.746],[-0.506,106.746],[-85.903,106.746],[0.506,-106.746]],"c":false}]}],"ix":2},"nm":"Path 1","mn":"ADBE Vector Shape - Group","hd":false},{"ty":"st","c":{"a":0,"k":[0.071,0.075,0.192,1],"ix":3,"x":"var $bm_rt;\n$bm_rt = comp('wired-lineal-1780-medal-first-place').layer('control').effect('primary')('Color');"},"o":{"a":0,"k":100,"ix":4},"w":{"a":0,"k":7,"ix":5,"x":"var $bm_rt;\n$bm_rt = $bm_mul($bm_div(value, 2), comp('wired-lineal-1780-medal-first-place').layer('control').effect('stroke')('Menu'));"},"lc":2,"lj":2,"bm":0,"nm":".primary","mn":"ADBE Vector Graphic - Stroke","hd":false,"cl":"primary"},{"ty":"tr","p":{"a":0,"k":[293.03,196.627],"ix":2},"a":{"a":0,"k":[0,0],"ix":1},"s":{"a":0,"k":[100,100],"ix":3},"r":{"a":0,"k":0,"ix":6},"o":{"a":0,"k":100,"ix":7},"sk":{"a":0,"k":0,"ix":4},"sa":{"a":0,"k":0,"ix":5},"nm":"Transform"}],"nm":"Group 2","np":2,"cix":2,"bm":0,"ix":1,"mn":"ADBE Vector Group","hd":false},{"ty":"tr","p":{"a":0,"k":[293.03,196.627],"ix":2},"a":{"a":0,"k":[293.03,196.627],"ix":1},"s":{"a":0,"k":[100,100],"ix":3},"r":{"a":0,"k":0,"ix":6},"o":{"a":0,"k":100,"ix":7},"sk":{"a":0,"k":0,"ix":4},"sa":{"a":0,"k":0,"ix":5},"nm":"Transform"}],"nm":"Group 2","np":1,"cix":2,"bm":0,"ix":1,"mn":"ADBE Vector Group","hd":false},{"ty":"gr","it":[{"ind":0,"ty":"sh","ix":1,"ks":{"a":1,"k":[{"i":{"x":0.833,"y":0.833},"o":{"x":0.167,"y":0.167},"t":24,"s":[{"i":[[0,0],[-1.047,0.846]],"o":[[0,0],[0,0]],"v":[[-58.669,-104.756],[-57.414,-89.122]],"c":false}]},{"i":{"x":0.833,"y":0.833},"o":{"x":0.167,"y":0.167},"t":34,"s":[{"i":[[0,0],[82.647,-51.995]],"o":[[0,0],[0,0]],"v":[[27.005,-103.615],[-93.632,40.547]],"c":false}]},{"i":{"x":0.833,"y":0.833},"o":{"x":0.167,"y":0.167},"t":38,"s":[{"i":[[0,0],[72.689,-63.41]],"o":[[0,0],[0,0]],"v":[[31.466,-103.615],[-99.341,110.14]],"c":false}]},{"i":{"x":0.833,"y":0.833},"o":{"x":0.167,"y":0.167},"t":42,"s":[{"i":[[0,0],[62.731,-74.825]],"o":[[0,0],[0,0]],"v":[[35.927,-103.615],[-77.693,144.049]],"c":false}]},{"i":{"x":0.833,"y":0.833},"o":{"x":0.167,"y":0.167},"t":46,"s":[{"i":[[0,0],[35.554,-78.978]],"o":[[0,0],[0,0]],"v":[[41.544,-103.615],[-46.007,140.852]],"c":false}]},{"i":{"x":0.833,"y":0.833},"o":{"x":0.167,"y":0.167},"t":51,"s":[{"i":[[0,0],[20.305,-79.383]],"o":[[0,0],[0,0]],"v":[[41.874,-103.615],[-16.361,123.622]],"c":false}]},{"i":{"x":0.833,"y":0.833},"o":{"x":0.167,"y":0.167},"t":55,"s":[{"i":[[0,0],[11.863,-78.18]],"o":[[0,0],[0,0]],"v":[[41.874,-103.615],[-19.001,112.281]],"c":false}]},{"i":{"x":0.667,"y":1},"o":{"x":0.167,"y":0.167},"t":62,"s":[{"i":[[0,0],[22.508,-71.023]],"o":[[0,0],[0,0]],"v":[[41.874,-103.615],[-35.65,96.726]],"c":false}]},{"i":{"x":0.667,"y":1},"o":{"x":0.333,"y":0},"t":70,"s":[{"i":[[0,0],[30.953,-67.77]],"o":[[0,0],[0,0]],"v":[[41.874,-103.615],[-45.908,98.298]],"c":false}]},{"t":84,"s":[{"i":[[0,0],[27.916,-69.077]],"o":[[0,0],[0,0]],"v":[[41.874,-103.615],[-41.874,103.615]],"c":false}]}],"ix":2},"nm":"Path 1","mn":"ADBE Vector Shape - Group","hd":false},{"ty":"st","c":{"a":0,"k":[0.071,0.075,0.192,1],"ix":3,"x":"var $bm_rt;\n$bm_rt = comp('wired-lineal-1780-medal-first-place').layer('control').effect('primary')('Color');"},"o":{"a":0,"k":100,"ix":4},"w":{"a":0,"k":7,"ix":5,"x":"var $bm_rt;\n$bm_rt = $bm_mul($bm_div(value, 2), comp('wired-lineal-1780-medal-first-place').layer('control').effect('stroke')('Menu'));"},"lc":2,"lj":2,"bm":0,"nm":".primary","mn":"ADBE Vector Graphic - Stroke","hd":false,"cl":"primary"},{"ty":"tr","p":{"a":0,"k":[293.461,193.776],"ix":2},"a":{"a":0,"k":[0,0],"ix":1},"s":{"a":0,"k":[100,100],"ix":3},"r":{"a":0,"k":0,"ix":6},"o":{"a":0,"k":100,"ix":7},"sk":{"a":0,"k":0,"ix":4},"sa":{"a":0,"k":0,"ix":5},"nm":"Transform"}],"nm":"Group 3","np":2,"cix":2,"bm":0,"ix":2,"mn":"ADBE Vector Group","hd":false},{"ty":"tm","s":{"a":0,"k":0,"ix":1},"e":{"a":0,"k":100,"ix":2},"o":{"a":0,"k":0,"ix":3},"m":1,"ix":3,"nm":"Trim Paths 1","mn":"ADBE Vector Filter - Trim","hd":false}],"ip":0,"op":844,"st":0,"ct":1,"bm":0},{"ddd":0,"ind":6,"ty":4,"nm":"mask","parent":5,"td":1,"sr":1,"ks":{"o":{"a":0,"k":100,"ix":11},"r":{"a":0,"k":0,"ix":10},"p":{"a":0,"k":[250,196.627,0],"ix":2,"l":2},"a":{"a":0,"k":[250,196.627,0],"ix":1,"l":2},"s":{"a":0,"k":[100,100,100],"ix":6,"l":2}},"ao":0,"shapes":[{"ty":"gr","it":[{"ty":"gr","it":[{"ind":0,"ty":"sh","ix":1,"ks":{"a":1,"k":[{"i":{"x":0.833,"y":0.833},"o":{"x":0.167,"y":0.167},"t":24,"s":[{"i":[[-13.602,1.804],[0,0],[0,0],[0.438,-3.575]],"o":[[-1.36,-4.243],[0,0],[0,0],[9.468,-0.377]],"v":[[-45.64,-78.507],[-45.122,-93.837],[-84.783,-93.706],[-85.938,-75.925]],"c":true}]},{"i":{"x":0.833,"y":0.833},"o":{"x":0.167,"y":0.167},"t":26,"s":[{"i":[[-13.152,-0.099],[0,0],[0,0],[17.376,-13.38]],"o":[[22.154,-7.974],[0,0],[0,0],[9.038,0.903]],"v":[[-53.404,-44.526],[-27.372,-93.737],[-67.883,-93.656],[-94.351,-49.545]],"c":true}]},{"i":{"x":0.833,"y":0.833},"o":{"x":0.167,"y":0.167},"t":28,"s":[{"i":[[-12.701,-2.002],[0,0],[0,0],[34.314,-23.186]],"o":[[38.919,-16.455],[0,0],[0,0],[8.607,2.183]],"v":[[-64.669,-13.545],[-9.622,-93.637],[-50.983,-93.606],[-102.764,-23.164]],"c":true}]},{"i":{"x":0.833,"y":0.833},"o":{"x":0.167,"y":0.167},"t":34,"s":[{"i":[[-11.349,-7.711],[0,0],[0,0],[85.128,-52.602]],"o":[[88.276,-49.336],[0,0],[0,0],[7.315,6.023]],"v":[[-93.213,83.899],[43.628,-93.337],[-0.283,-93.456],[-128.003,55.977]],"c":true}]},{"i":{"x":0.833,"y":0.833},"o":{"x":0.167,"y":0.167},"t":38,"s":[{"i":[[-12.224,-6.586],[0,0],[0,0],[72.378,-53.852]],"o":[[67.276,-69.336],[0,0],[0,0],[11.128,5.398]],"v":[[-95.526,148.336],[48.628,-93.337],[4.717,-93.456],[-134.878,125.602]],"c":true}]},{"i":{"x":0.833,"y":0.833},"o":{"x":0.167,"y":0.167},"t":42,"s":[{"i":[[-13.849,1.1],[0,0],[0,0],[58.628,-75.602]],"o":[[52.776,-70.086],[0,0],[0,0],[11.503,-0.237]],"v":[[-67.026,163.836],[52.128,-93.337],[8.217,-93.456],[-91.628,132.352]],"c":true}]},{"i":{"x":0.833,"y":0.833},"o":{"x":0.167,"y":0.167},"t":46,"s":[{"i":[[-13.849,1.1],[0,0],[0,0],[25.878,-63.102]],"o":[[36.276,-79.086],[0,0],[0,0],[11.503,-0.237]],"v":[[-34.776,163.586],[57.128,-92.837],[13.217,-92.956],[-67.128,141.352]],"c":true}]},{"i":{"x":0.833,"y":0.833},"o":{"x":0.167,"y":0.167},"t":51,"s":[{"i":[[-13.849,1.1],[0,0],[0,0],[14.378,-71.852]],"o":[[22.276,-81.836],[0,0],[0,0],[11.503,-0.237]],"v":[[-3.276,140.336],[57.128,-92.837],[13.217,-92.956],[-41.878,136.852]],"c":true}]},{"i":{"x":0.833,"y":0.833},"o":{"x":0.167,"y":0.167},"t":55,"s":[{"i":[[-13.849,1.1],[0,0],[0,0],[14.378,-71.852]],"o":[[14.526,-84.336],[0,0],[0,0],[11.503,-0.237]],"v":[[-6.276,124.836],[57.128,-92.837],[13.217,-92.956],[-50.878,127.852]],"c":true}]},{"i":{"x":0.833,"y":1},"o":{"x":0.167,"y":0.167},"t":62,"s":[{"i":[[-13.849,1.1],[0,0],[0,0],[26.885,-68.57]],"o":[[25.151,-79.566],[0,0],[0,0],[11.503,-0.237]],"v":[[-21.276,110.336],[57.128,-92.837],[13.217,-92.956],[-65.878,113.352]],"c":true}]},{"i":{"x":0.833,"y":1},"o":{"x":0.167,"y":0},"t":70,"s":[{"i":[[-13.349,-1.95],[0,0],[0,0],[26.885,-68.57]],"o":[[31.651,-74.262],[0,0],[0,0],[9.378,1.487]],"v":[[-32.151,118.08],[57.128,-92.837],[13.217,-92.956],[-74.128,114.643]],"c":true}]},{"t":84,"s":[{"i":[[-12.217,-3.055],[0,0],[0,0],[26.885,-68.57]],"o":[[25.658,-64.18],[0,0],[0,0],[1.885,9.43]],"v":[[-29.151,119.962],[57.128,-92.837],[13.217,-92.956],[-55.628,78.352]],"c":true}]}],"ix":2},"nm":"Path 1","mn":"ADBE Vector Shape - Group","hd":false},{"ty":"fl","c":{"a":0,"k":[0.949019610882,0.298039227724,0,1],"ix":4},"o":{"a":0,"k":100,"ix":5},"r":1,"bm":0,"nm":".tertiary","mn":"ADBE Vector Graphic - Fill","hd":false,"cl":"tertiary"},{"ty":"tr","p":{"a":0,"k":[321,182.75],"ix":2},"a":{"a":0,"k":[0,0],"ix":1},"s":{"a":0,"k":[100,100],"ix":3},"r":{"a":0,"k":0,"ix":6},"o":{"a":0,"k":100,"ix":7},"sk":{"a":0,"k":0,"ix":4},"sa":{"a":0,"k":0,"ix":5},"nm":"Transform"}],"nm":"Group 1","np":2,"cix":2,"bm":0,"ix":1,"mn":"ADBE Vector Group","hd":false},{"ty":"gr","it":[{"ind":0,"ty":"sh","ix":1,"ks":{"a":1,"k":[{"i":{"x":0.833,"y":0.833},"o":{"x":0.167,"y":0.167},"t":24,"s":[{"i":[[0,0],[-0.149,-0.618],[-0.218,-0.617],[0,0]],"o":[[0,0],[-25.538,4.085],[-2.426,-31.227],[0,0]],"v":[[-16.347,-107.746],[-17.631,-92.509],[-99.604,-89.9],[-101.744,-107.746]],"c":false}]},{"i":{"x":0.833,"y":0.833},"o":{"x":0.167,"y":0.167},"t":26,"s":[{"i":[[0,0],[13.726,-11.861],[-0.125,-0.615],[0,0]],"o":[[0,0],[-24.785,0.477],[12.309,-36.721],[0,0]],"v":[[1.403,-107.646],[-25.381,-58.516],[-105.289,-68.456],[-83.994,-107.646]],"c":false}]},{"i":{"x":0.833,"y":0.833},"o":{"x":0.167,"y":0.167},"t":28,"s":[{"i":[[0,0],[27.601,-23.103],[-0.032,-0.612],[0,0]],"o":[[0,0],[-24.033,-3.132],[27.044,-42.215],[0,0]],"v":[[19.153,-107.546],[-36.631,-27.523],[-110.974,-47.012],[-66.244,-107.546]],"c":false}]},{"i":{"x":0.833,"y":0.833},"o":{"x":0.167,"y":0.167},"t":34,"s":[{"i":[[0,0],[56.226,-64.707],[0.248,-0.606],[0,0]],"o":[[0,0],[-21.774,-13.957],[71.248,-58.697],[0,0]],"v":[[72.403,-107.246],[-65.131,69.955],[-128.028,17.32],[-12.994,-107.246]],"c":false}]},{"i":{"x":0.833,"y":0.833},"o":{"x":0.167,"y":0.167},"t":38,"s":[{"i":[[0,0],[33.726,-68.207],[0.248,-0.606],[0,0]],"o":[[0,0],[-23.024,-10.207],[63.748,-67.197],[0,0]],"v":[[77.403,-107.246],[-67.506,133.83],[-138.778,90.07],[-7.994,-107.246]],"c":false}]},{"i":{"x":0.833,"y":0.833},"o":{"x":0.167,"y":0.167},"t":42,"s":[{"i":[[0,0],[33.726,-68.207],[0.248,-0.606],[0,0]],"o":[[0,0],[-32.774,3.666],[34.998,-88.947],[0,0]],"v":[[80.903,-107.246],[-39.006,149.33],[-94.278,110.82],[-4.494,-107.246]],"c":false}]},{"i":{"x":0.833,"y":0.833},"o":{"x":0.167,"y":0.167},"t":46,"s":[{"i":[[0,0],[16.226,-73.707],[0.248,-0.606],[0,0]],"o":[[0,0],[-32.774,3.666],[26.748,-92.947],[0,0]],"v":[[85.903,-106.746],[-6.756,149.08],[-77.028,122.82],[0.506,-106.746]],"c":false}]},{"i":{"x":0.833,"y":0.833},"o":{"x":0.167,"y":0.167},"t":51,"s":[{"i":[[0,0],[16.226,-73.707],[0.248,-0.606],[0,0]],"o":[[0,0],[-32.774,3.666],[12.498,-101.197],[0,0]],"v":[[85.903,-106.746],[24.744,125.83],[-51.028,126.32],[0.506,-106.746]],"c":false}]},{"i":{"x":0.833,"y":0.833},"o":{"x":0.167,"y":0.167},"t":55,"s":[{"i":[[0,0],[11.726,-74.957],[0.248,-0.606],[0,0]],"o":[[0,0],[-32.774,3.666],[9.748,-101.447],[0,0]],"v":[[85.903,-106.746],[21.744,110.33],[-61.028,122.82],[0.506,-106.746]],"c":false}]},{"i":{"x":0.833,"y":1},"o":{"x":0.167,"y":0.167},"t":62,"s":[{"i":[[0,0],[17.476,-71.709],[0.248,-0.606],[0,0]],"o":[[0,0],[-32.774,3.666],[15.498,-75.98],[0,0]],"v":[[85.903,-106.746],[6.744,95.83],[-78.278,103.07],[0.506,-106.746]],"c":false}]},{"i":{"x":0.833,"y":1},"o":{"x":0.167,"y":0},"t":70,"s":[{"i":[[0,0],[26.976,-68.373],[0,0],[0,0]],"o":[[0,0],[-32.524,-1.267],[0,0],[0,0]],"v":[[85.903,-106.746],[-3.506,104.864],[-88.903,98.682],[0.506,-106.746]],"c":false}]},{"t":84,"s":[{"i":[[0,0],[26.976,-68.373],[0,0],[0,0]],"o":[[0,0],[-33.524,0.127],[0,0],[0,0]],"v":[[85.903,-106.746],[-0.506,106.746],[-85.903,106.746],[0.506,-106.746]],"c":false}]}],"ix":2},"nm":"Path 1","mn":"ADBE Vector Shape - Group","hd":false},{"ty":"fl","c":{"a":0,"k":[0.921568632126,0.901960790157,0.937254905701,1],"ix":4},"o":{"a":0,"k":100,"ix":5},"r":1,"bm":0,"nm":".secondary","mn":"ADBE Vector Graphic - Fill","hd":false,"cl":"secondary"},{"ty":"tr","p":{"a":0,"k":[293.03,196.627],"ix":2},"a":{"a":0,"k":[0,0],"ix":1},"s":{"a":0,"k":[100,100],"ix":3},"r":{"a":0,"k":0,"ix":6},"o":{"a":0,"k":100,"ix":7},"sk":{"a":0,"k":0,"ix":4},"sa":{"a":0,"k":0,"ix":5},"nm":"Transform"}],"nm":"Group 2","np":2,"cix":2,"bm":0,"ix":2,"mn":"ADBE Vector Group","hd":false},{"ty":"tr","p":{"a":0,"k":[293.03,196.627],"ix":2},"a":{"a":0,"k":[293.03,196.627],"ix":1},"s":{"a":0,"k":[100,100],"ix":3},"r":{"a":0,"k":0,"ix":6},"o":{"a":0,"k":100,"ix":7},"sk":{"a":0,"k":0,"ix":4},"sa":{"a":0,"k":0,"ix":5},"nm":"Transform"}],"nm":"Group 2","np":2,"cix":2,"bm":0,"ix":1,"mn":"ADBE Vector Group","hd":false}],"ip":24,"op":860,"st":16,"ct":1,"bm":0},{"ddd":0,"ind":7,"ty":4,"nm":"Ribbon fill 2","parent":2,"tt":1,"tp":6,"sr":1,"ks":{"o":{"a":0,"k":50,"ix":11},"r":{"a":0,"k":0,"ix":10},"p":{"a":0,"k":[264.5,196.627,0],"ix":2,"l":2},"a":{"a":0,"k":[250,196.627,0],"ix":1,"l":2},"s":{"a":0,"k":[100,100,100],"ix":6,"l":2}},"ao":0,"shapes":[{"ty":"gr","it":[{"ind":0,"ty":"sh","ix":1,"ks":{"a":1,"k":[{"i":{"x":0.833,"y":0.833},"o":{"x":0.167,"y":0.167},"t":24,"s":[{"i":[[0,0],[-2.338,-67.869],[-27.14,-0.236],[0,0]],"o":[[0,0],[28.197,0.273],[0.61,-5.736],[0,0]],"v":[[-12.155,-107.859],[-12.792,-92.4],[70.42,-91.391],[70.492,-107.859]],"c":false}]},{"i":{"x":0.833,"y":0.833},"o":{"x":0.167,"y":0.167},"t":34,"s":[{"i":[[0,0],[7.928,-68.492],[-26.648,-5.533],[0,0]],"o":[[0,0],[29.404,8.105],[-17.148,-129.033],[0,0]],"v":[[-69.135,-104.989],[-43.124,19.768],[39.178,38.906],[13.762,-105.989]],"c":false}]},{"i":{"x":0.833,"y":0.833},"o":{"x":0.167,"y":0.167},"t":38,"s":[{"i":[[0,0],[12.034,-68.741],[-26.401,-2.562],[0,0]],"o":[[0,0],[28.376,3.668],[-9.022,-183.042],[0,0]],"v":[[-74.427,-105.341],[-50.493,93.638],[32.004,119.499],[10.97,-105.341]],"c":false}]},{"i":{"x":0.833,"y":0.833},"o":{"x":0.167,"y":0.167},"t":42,"s":[{"i":[[0,0],[16.141,-68.991],[-26.667,-2.845],[0,0]],"o":[[0,0],[28.782,3.988],[-6.722,-194.323],[0,0]],"v":[[-80.403,-105.746],[-34.861,130.114],[46.501,163.946],[4.994,-105.746]],"c":false}]},{"i":{"x":0.833,"y":0.833},"o":{"x":0.167,"y":0.167},"t":46,"s":[{"i":[[0,0],[-8.312,-78.192],[-26.933,-3.128],[0,0]],"o":[[0,0],[29.188,4.308],[-4.683,-71.378],[0,0]],"v":[[-85.903,-106.746],[-2.908,137.815],[79.713,156.251],[-0.506,-106.746]],"c":false}]},{"i":{"x":0.833,"y":0.833},"o":{"x":0.167,"y":0.167},"t":51,"s":[{"i":[[0,0],[-35.295,-73.901],[-26.684,-0.229],[0,0]],"o":[[0,0],[29.505,-2.237],[-36.299,-76.775],[0,0]],"v":[[-85.903,-106.746],[25.824,129.274],[112.579,128.648],[-0.506,-106.746]],"c":false}]},{"i":{"x":0.833,"y":0.833},"o":{"x":0.167,"y":0.167},"t":55,"s":[{"i":[[0,0],[-35.955,-68.767],[-28.788,4.281],[0,0]],"o":[[0,0],[29.896,-2.462],[-42.443,-72.84],[0,0]],"v":[[-85.903,-106.746],[25.384,121.335],[108.318,110.592],[-0.506,-106.746]],"c":false}]},{"i":{"x":0.833,"y":0.833},"o":{"x":0.167,"y":0.167},"t":62,"s":[{"i":[[0,0],[-37.098,-69.071],[-27.291,-0.306],[0,0]],"o":[[0,0],[24.524,0.627],[-43.916,-72.454],[0,0]],"v":[[-85.903,-106.746],[4.877,96.419],[92.571,90.509],[-0.506,-106.746]],"c":false}]},{"i":{"x":0.667,"y":1},"o":{"x":0.167,"y":0.167},"t":70,"s":[{"i":[[0,0],[-26.976,-66.373],[-24.373,-1.536],[0,0]],"o":[[0,0],[24.524,0.627],[-30.873,-75.873],[0,0]],"v":[[-85.903,-106.746],[-11.494,94.649],[72.403,99.488],[-0.506,-106.746]],"c":false}]},{"t":84,"s":[{"i":[[0,0],[-26.976,-66.373],[-23.873,0.127],[0,0]],"o":[[0,0],[24.524,0.627],[-30.873,-75.873],[0,0]],"v":[[-85.903,-106.746],[0.506,106.746],[85.903,106.746],[-0.506,-106.746]],"c":false}]}],"ix":2},"nm":"Path 1","mn":"ADBE Vector Shape - Group","hd":false},{"ty":"fl","c":{"a":0,"k":[0.922,0.902,0.937,1],"ix":4,"x":"var $bm_rt;\n$bm_rt = comp('wired-lineal-1780-medal-first-place').layer('control').effect('tertiary')('Color');"},"o":{"a":0,"k":100,"ix":5},"r":1,"bm":0,"nm":".tertiary","mn":"ADBE Vector Graphic - Fill","hd":false,"cl":"tertiary"},{"ty":"tr","p":{"a":0,"k":[206.97,196.627],"ix":2},"a":{"a":0,"k":[0,0],"ix":1},"s":{"a":0,"k":[100,100],"ix":3},"r":{"a":0,"k":0,"ix":6},"o":{"a":0,"k":100,"ix":7},"sk":{"a":0,"k":0,"ix":4},"sa":{"a":0,"k":0,"ix":5},"nm":"Transform"}],"nm":"Group 1","np":3,"cix":2,"bm":0,"ix":1,"mn":"ADBE Vector Group","hd":false}],"ip":0,"op":844,"st":0,"ct":1,"bm":1},{"ddd":0,"ind":8,"ty":4,"nm":"Ribbon 4 fill","parent":5,"sr":1,"ks":{"o":{"a":0,"k":100,"ix":11},"r":{"a":0,"k":0,"ix":10},"p":{"a":0,"k":[250,196.627,0],"ix":2,"l":2},"a":{"a":0,"k":[250,196.627,0],"ix":1,"l":2},"s":{"a":0,"k":[100,100,100],"ix":6,"l":2}},"ao":0,"shapes":[{"ty":"gr","it":[{"ty":"gr","it":[{"ind":0,"ty":"sh","ix":1,"ks":{"a":1,"k":[{"i":{"x":0.833,"y":0.833},"o":{"x":0.167,"y":0.167},"t":24,"s":[{"i":[[-13.602,1.804],[0,0],[0,0],[0.438,-3.575]],"o":[[-1.36,-4.243],[0,0],[0,0],[9.468,-0.377]],"v":[[-45.64,-78.507],[-45.122,-93.837],[-84.783,-93.706],[-85.938,-75.925]],"c":true}]},{"i":{"x":0.833,"y":0.833},"o":{"x":0.167,"y":0.167},"t":26,"s":[{"i":[[-13.152,-0.099],[0,0],[0,0],[17.376,-13.38]],"o":[[22.154,-7.974],[0,0],[0,0],[9.038,0.903]],"v":[[-53.404,-44.526],[-27.372,-93.737],[-67.883,-93.656],[-94.351,-49.545]],"c":true}]},{"i":{"x":0.833,"y":0.833},"o":{"x":0.167,"y":0.167},"t":28,"s":[{"i":[[-12.701,-2.002],[0,0],[0,0],[34.314,-23.186]],"o":[[38.919,-16.455],[0,0],[0,0],[8.607,2.183]],"v":[[-64.669,-13.545],[-9.622,-93.637],[-50.983,-93.606],[-102.764,-23.164]],"c":true}]},{"i":{"x":0.833,"y":0.833},"o":{"x":0.167,"y":0.167},"t":34,"s":[{"i":[[-11.349,-7.711],[0,0],[0,0],[85.128,-52.602]],"o":[[88.276,-49.336],[0,0],[0,0],[7.315,6.023]],"v":[[-93.213,83.899],[43.628,-93.337],[-0.283,-93.456],[-128.003,55.977]],"c":true}]},{"i":{"x":0.833,"y":0.833},"o":{"x":0.167,"y":0.167},"t":38,"s":[{"i":[[-12.224,-6.586],[0,0],[0,0],[72.378,-53.852]],"o":[[67.276,-69.336],[0,0],[0,0],[11.128,5.398]],"v":[[-95.526,148.336],[48.628,-93.337],[4.717,-93.456],[-134.878,125.602]],"c":true}]},{"i":{"x":0.833,"y":0.833},"o":{"x":0.167,"y":0.167},"t":42,"s":[{"i":[[-13.849,1.1],[0,0],[0,0],[58.628,-75.602]],"o":[[52.776,-70.086],[0,0],[0,0],[11.503,-0.237]],"v":[[-67.026,163.836],[52.128,-93.337],[8.217,-93.456],[-91.628,132.352]],"c":true}]},{"i":{"x":0.833,"y":0.833},"o":{"x":0.167,"y":0.167},"t":46,"s":[{"i":[[-13.849,1.1],[0,0],[0,0],[25.878,-63.102]],"o":[[36.276,-79.086],[0,0],[0,0],[11.503,-0.237]],"v":[[-34.776,163.586],[57.128,-92.837],[13.217,-92.956],[-67.128,141.352]],"c":true}]},{"i":{"x":0.833,"y":0.833},"o":{"x":0.167,"y":0.167},"t":51,"s":[{"i":[[-13.849,1.1],[0,0],[0,0],[14.378,-71.852]],"o":[[22.276,-81.836],[0,0],[0,0],[11.503,-0.237]],"v":[[-3.276,140.336],[57.128,-92.837],[13.217,-92.956],[-41.878,136.852]],"c":true}]},{"i":{"x":0.833,"y":0.833},"o":{"x":0.167,"y":0.167},"t":55,"s":[{"i":[[-13.849,1.1],[0,0],[0,0],[14.378,-71.852]],"o":[[14.526,-84.336],[0,0],[0,0],[11.503,-0.237]],"v":[[-6.276,124.836],[57.128,-92.837],[13.217,-92.956],[-50.878,127.852]],"c":true}]},{"i":{"x":0.833,"y":1},"o":{"x":0.167,"y":0.167},"t":62,"s":[{"i":[[-13.849,1.1],[0,0],[0,0],[26.885,-68.57]],"o":[[25.151,-79.566],[0,0],[0,0],[11.503,-0.237]],"v":[[-21.276,110.336],[57.128,-92.837],[13.217,-92.956],[-65.878,113.352]],"c":true}]},{"i":{"x":0.833,"y":1},"o":{"x":0.167,"y":0},"t":70,"s":[{"i":[[-13.349,-1.95],[0,0],[0,0],[26.885,-68.57]],"o":[[31.651,-74.262],[0,0],[0,0],[9.378,1.487]],"v":[[-32.151,118.08],[57.128,-92.837],[13.217,-92.956],[-74.128,114.643]],"c":true}]},{"t":84,"s":[{"i":[[-12.217,-3.055],[0,0],[0,0],[26.885,-68.57]],"o":[[25.658,-64.18],[0,0],[0,0],[1.885,9.43]],"v":[[-29.151,119.962],[57.128,-92.837],[13.217,-92.956],[-55.628,78.352]],"c":true}]}],"ix":2},"nm":"Path 1","mn":"ADBE Vector Shape - Group","hd":false},{"ty":"fl","c":{"a":0,"k":[0.443,0.4,0.933,1],"ix":4,"x":"var $bm_rt;\n$bm_rt = comp('wired-lineal-1780-medal-first-place').layer('control').effect('quaternary')('Color');"},"o":{"a":0,"k":100,"ix":5},"r":1,"bm":0,"nm":".quaternary","mn":"ADBE Vector Graphic - Fill","hd":false,"cl":"quaternary"},{"ty":"tr","p":{"a":0,"k":[321,182.75],"ix":2},"a":{"a":0,"k":[0,0],"ix":1},"s":{"a":0,"k":[100,100],"ix":3},"r":{"a":0,"k":0,"ix":6},"o":{"a":0,"k":100,"ix":7},"sk":{"a":0,"k":0,"ix":4},"sa":{"a":0,"k":0,"ix":5},"nm":"Transform"}],"nm":"Group 1","np":2,"cix":2,"bm":0,"ix":1,"mn":"ADBE Vector Group","hd":false},{"ty":"gr","it":[{"ind":0,"ty":"sh","ix":1,"ks":{"a":1,"k":[{"i":{"x":0.833,"y":0.833},"o":{"x":0.167,"y":0.167},"t":24,"s":[{"i":[[0,0],[-0.149,-0.618],[-0.218,-0.617],[0,0]],"o":[[0,0],[-25.538,4.085],[-2.426,-31.227],[0,0]],"v":[[-16.347,-107.746],[-17.631,-92.509],[-99.604,-89.9],[-101.744,-107.746]],"c":false}]},{"i":{"x":0.833,"y":0.833},"o":{"x":0.167,"y":0.167},"t":26,"s":[{"i":[[0,0],[13.726,-11.861],[-0.125,-0.615],[0,0]],"o":[[0,0],[-24.785,0.477],[12.309,-36.721],[0,0]],"v":[[1.403,-107.646],[-25.381,-58.516],[-105.289,-68.456],[-83.994,-107.646]],"c":false}]},{"i":{"x":0.833,"y":0.833},"o":{"x":0.167,"y":0.167},"t":28,"s":[{"i":[[0,0],[27.601,-23.103],[-0.032,-0.612],[0,0]],"o":[[0,0],[-24.033,-3.132],[27.044,-42.215],[0,0]],"v":[[19.153,-107.546],[-36.631,-27.523],[-110.974,-47.012],[-66.244,-107.546]],"c":false}]},{"i":{"x":0.833,"y":0.833},"o":{"x":0.167,"y":0.167},"t":34,"s":[{"i":[[0,0],[56.226,-64.707],[0.248,-0.606],[0,0]],"o":[[0,0],[-21.774,-13.957],[71.248,-58.697],[0,0]],"v":[[72.403,-107.246],[-65.131,69.955],[-128.028,17.32],[-12.994,-107.246]],"c":false}]},{"i":{"x":0.833,"y":0.833},"o":{"x":0.167,"y":0.167},"t":38,"s":[{"i":[[0,0],[33.726,-68.207],[0.248,-0.606],[0,0]],"o":[[0,0],[-23.024,-10.207],[63.748,-67.197],[0,0]],"v":[[77.403,-107.246],[-67.506,133.83],[-138.778,90.07],[-7.994,-107.246]],"c":false}]},{"i":{"x":0.833,"y":0.833},"o":{"x":0.167,"y":0.167},"t":42,"s":[{"i":[[0,0],[33.726,-68.207],[0.248,-0.606],[0,0]],"o":[[0,0],[-32.774,3.666],[34.998,-88.947],[0,0]],"v":[[80.903,-107.246],[-39.006,149.33],[-94.278,110.82],[-4.494,-107.246]],"c":false}]},{"i":{"x":0.833,"y":0.833},"o":{"x":0.167,"y":0.167},"t":46,"s":[{"i":[[0,0],[16.226,-73.707],[0.248,-0.606],[0,0]],"o":[[0,0],[-32.774,3.666],[26.748,-92.947],[0,0]],"v":[[85.903,-106.746],[-6.756,149.08],[-77.028,122.82],[0.506,-106.746]],"c":false}]},{"i":{"x":0.833,"y":0.833},"o":{"x":0.167,"y":0.167},"t":51,"s":[{"i":[[0,0],[16.226,-73.707],[0.248,-0.606],[0,0]],"o":[[0,0],[-32.774,3.666],[12.498,-101.197],[0,0]],"v":[[85.903,-106.746],[24.744,125.83],[-51.028,126.32],[0.506,-106.746]],"c":false}]},{"i":{"x":0.833,"y":0.833},"o":{"x":0.167,"y":0.167},"t":55,"s":[{"i":[[0,0],[11.726,-74.957],[0.248,-0.606],[0,0]],"o":[[0,0],[-32.774,3.666],[9.748,-101.447],[0,0]],"v":[[85.903,-106.746],[21.744,110.33],[-61.028,122.82],[0.506,-106.746]],"c":false}]},{"i":{"x":0.833,"y":1},"o":{"x":0.167,"y":0.167},"t":62,"s":[{"i":[[0,0],[17.476,-71.709],[0.248,-0.606],[0,0]],"o":[[0,0],[-32.774,3.666],[15.498,-75.98],[0,0]],"v":[[85.903,-106.746],[6.744,95.83],[-78.278,103.07],[0.506,-106.746]],"c":false}]},{"i":{"x":0.833,"y":1},"o":{"x":0.167,"y":0},"t":70,"s":[{"i":[[0,0],[26.976,-68.373],[0,0],[0,0]],"o":[[0,0],[-32.524,-1.267],[0,0],[0,0]],"v":[[85.903,-106.746],[-3.506,104.864],[-88.903,98.682],[0.506,-106.746]],"c":false}]},{"t":84,"s":[{"i":[[0,0],[26.976,-68.373],[0,0],[0,0]],"o":[[0,0],[-33.524,0.127],[0,0],[0,0]],"v":[[85.903,-106.746],[-0.506,106.746],[-85.903,106.746],[0.506,-106.746]],"c":false}]}],"ix":2},"nm":"Path 1","mn":"ADBE Vector Shape - Group","hd":false},{"ty":"fl","c":{"a":0,"k":[0.922,0.902,0.937,1],"ix":4,"x":"var $bm_rt;\n$bm_rt = comp('wired-lineal-1780-medal-first-place').layer('control').effect('tertiary')('Color');"},"o":{"a":0,"k":100,"ix":5},"r":1,"bm":0,"nm":".tertiary","mn":"ADBE Vector Graphic - Fill","hd":false,"cl":"tertiary"},{"ty":"tr","p":{"a":0,"k":[293.03,196.627],"ix":2},"a":{"a":0,"k":[0,0],"ix":1},"s":{"a":0,"k":[100,100],"ix":3},"r":{"a":0,"k":0,"ix":6},"o":{"a":0,"k":100,"ix":7},"sk":{"a":0,"k":0,"ix":4},"sa":{"a":0,"k":0,"ix":5},"nm":"Transform"}],"nm":"Group 2","np":2,"cix":2,"bm":0,"ix":2,"mn":"ADBE Vector Group","hd":false},{"ty":"tr","p":{"a":0,"k":[293.03,196.627],"ix":2},"a":{"a":0,"k":[293.03,196.627],"ix":1},"s":{"a":0,"k":[100,100],"ix":3},"r":{"a":0,"k":0,"ix":6},"o":{"a":0,"k":100,"ix":7},"sk":{"a":0,"k":0,"ix":4},"sa":{"a":0,"k":0,"ix":5},"nm":"Transform"}],"nm":"Group 2","np":2,"cix":2,"bm":0,"ix":1,"mn":"ADBE Vector Group","hd":false}],"ip":24,"op":860,"st":16,"ct":1,"bm":0}]},{"id":"comp_2","nm":"hover-pinch","fr":60,"layers":[{"ddd":0,"ind":1,"ty":4,"nm":"Medal","sr":1,"ks":{"o":{"a":0,"k":100,"ix":11},"r":{"a":1,"k":[{"i":{"x":[0.015],"y":[1]},"o":{"x":[0.167],"y":[0.167]},"t":0,"s":[0]},{"i":{"x":[0.667],"y":[1]},"o":{"x":[0.333],"y":[0]},"t":30,"s":[15]},{"i":{"x":[0.667],"y":[1]},"o":{"x":[0.333],"y":[0]},"t":50,"s":[-16]},{"i":{"x":[0.667],"y":[1]},"o":{"x":[0.333],"y":[0]},"t":70,"s":[2.235]},{"i":{"x":[0.667],"y":[1]},"o":{"x":[0.333],"y":[0]},"t":92,"s":[-2.975]},{"t":117,"s":[0]}],"ix":10},"p":{"a":0,"k":[215,14.615,0],"ix":2,"l":2},"a":{"a":0,"k":[250,49.615,0],"ix":1,"l":2},"s":{"a":0,"k":[100,100,100],"ix":6,"l":2}},"ao":0,"shapes":[{"ty":"gr","it":[{"ty":"gr","it":[{"ind":0,"ty":"sh","ix":1,"ks":{"a":0,"k":{"i":[[0,0],[0,0],[0,0]],"o":[[0,0],[0,0],[0,0]],"v":[[-7.23,-8.452],[7.23,-22.912],[7.23,22.912]],"c":false},"ix":2},"nm":"Path 1","mn":"ADBE Vector Shape - Group","hd":false},{"ty":"st","c":{"a":0,"k":[0.698,0.408,0.212,1],"ix":3,"x":"var $bm_rt;\n$bm_rt = comp('wired-lineal-1780-medal-first-place').layer('control').effect('quinary')('Color');"},"o":{"a":0,"k":100,"ix":4},"w":{"a":0,"k":7,"ix":5,"x":"var $bm_rt;\n$bm_rt = $bm_mul($bm_div(value, 2), comp('wired-lineal-1780-medal-first-place').layer('control').effect('stroke')('Menu'));"},"lc":2,"lj":2,"bm":0,"nm":".quinary","mn":"ADBE Vector Graphic - Stroke","hd":false,"cl":"quinary"},{"ty":"tr","p":{"a":0,"k":[245.636,332.114],"ix":2},"a":{"a":0,"k":[0,0],"ix":1},"s":{"a":0,"k":[100,100],"ix":3},"r":{"a":0,"k":0,"ix":6},"o":{"a":0,"k":100,"ix":7},"sk":{"a":0,"k":0,"ix":4},"sa":{"a":0,"k":0,"ix":5},"nm":"Transform"}],"nm":"Group 2","np":2,"cix":2,"bm":0,"ix":1,"mn":"ADBE Vector Group","hd":false},{"ty":"gr","it":[{"ind":0,"ty":"sh","ix":1,"ks":{"a":0,"k":{"i":[[0,29.427],[-29.427,0],[0,-29.427],[29.427,0]],"o":[[0,-29.427],[29.427,0],[0,29.427],[-29.427,0]],"v":[[-53.281,0],[0,-53.281],[53.281,0],[0,53.281]],"c":true},"ix":2},"nm":"Path 1","mn":"ADBE Vector Shape - Group","hd":false},{"ty":"st","c":{"a":0,"k":[0.698,0.408,0.212,1],"ix":3,"x":"var $bm_rt;\n$bm_rt = comp('wired-lineal-1780-medal-first-place').layer('control').effect('quinary')('Color');"},"o":{"a":0,"k":100,"ix":4},"w":{"a":0,"k":7,"ix":5,"x":"var $bm_rt;\n$bm_rt = $bm_mul($bm_div(value, 2), comp('wired-lineal-1780-medal-first-place').layer('control').effect('stroke')('Menu'));"},"lc":2,"lj":2,"bm":0,"d":[{"n":"d","nm":"dash","v":{"a":0,"k":0.1,"ix":1}},{"n":"g","nm":"gap","v":{"a":0,"k":28,"ix":2}}],"nm":".quinary","mn":"ADBE Vector Graphic - Stroke","hd":false,"cl":"quinary"},{"ty":"tr","p":{"a":0,"k":[250,332.114],"ix":2},"a":{"a":0,"k":[0,0],"ix":1},"s":{"a":0,"k":[100,100],"ix":3},"r":{"a":0,"k":0,"ix":6},"o":{"a":0,"k":100,"ix":7},"sk":{"a":0,"k":0,"ix":4},"sa":{"a":0,"k":0,"ix":5},"nm":"Transform"}],"nm":"Group 3","np":2,"cix":2,"bm":0,"ix":2,"mn":"ADBE Vector Group","hd":false},{"ty":"gr","it":[{"ind":0,"ty":"sh","ix":1,"ks":{"a":0,"k":{"i":[[0,43.081],[-43.081,0],[0,-43.081],[43.081,0]],"o":[[0,-43.081],[43.081,0],[0,43.081],[-43.081,0]],"v":[[-78.005,0],[0,-78.005],[78.005,0],[0,78.005]],"c":true},"ix":2},"nm":"Path 1","mn":"ADBE Vector Shape - Group","hd":false},{"ty":"st","c":{"a":0,"k":[0.071,0.075,0.192,1],"ix":3,"x":"var $bm_rt;\n$bm_rt = comp('wired-lineal-1780-medal-first-place').layer('control').effect('primary')('Color');"},"o":{"a":0,"k":100,"ix":4},"w":{"a":0,"k":7,"ix":5,"x":"var $bm_rt;\n$bm_rt = $bm_mul($bm_div(value, 2), comp('wired-lineal-1780-medal-first-place').layer('control').effect('stroke')('Menu'));"},"lc":2,"lj":2,"bm":0,"nm":".primary","mn":"ADBE Vector Graphic - Stroke","hd":false,"cl":"primary"},{"ty":"tr","p":{"a":0,"k":[250,332.114],"ix":2},"a":{"a":0,"k":[0,0],"ix":1},"s":{"a":0,"k":[100,100],"ix":3},"r":{"a":0,"k":0,"ix":6},"o":{"a":0,"k":100,"ix":7},"sk":{"a":0,"k":0,"ix":4},"sa":{"a":0,"k":0,"ix":5},"nm":"Transform"}],"nm":"Group 4","np":2,"cix":2,"bm":0,"ix":3,"mn":"ADBE Vector Group","hd":false},{"ty":"tr","p":{"a":0,"k":[250,332.114],"ix":2},"a":{"a":0,"k":[250,332.114],"ix":1},"s":{"a":0,"k":[100,100],"ix":3},"r":{"a":1,"k":[{"i":{"x":[0.667],"y":[1]},"o":{"x":[0.167],"y":[0.167]},"t":0,"s":[0]},{"i":{"x":[0.667],"y":[1]},"o":{"x":[0.333],"y":[0]},"t":35,"s":[7]},{"i":{"x":[0.667],"y":[1]},"o":{"x":[0.333],"y":[0]},"t":55,"s":[-10]},{"i":{"x":[0.667],"y":[1]},"o":{"x":[0.333],"y":[0]},"t":75,"s":[2]},{"i":{"x":[0.667],"y":[1]},"o":{"x":[0.333],"y":[0]},"t":97,"s":[-1]},{"t":122,"s":[0]}],"ix":6},"o":{"a":0,"k":100,"ix":7},"sk":{"a":0,"k":0,"ix":4},"sa":{"a":0,"k":0,"ix":5},"nm":"Transform"}],"nm":"Group 1","np":3,"cix":2,"bm":0,"ix":1,"mn":"ADBE Vector Group","hd":false}],"ip":0,"op":844,"st":0,"ct":1,"bm":0},{"ddd":0,"ind":2,"ty":4,"nm":"Warstwa 3","parent":1,"sr":1,"ks":{"o":{"a":0,"k":50,"ix":11},"r":{"a":0,"k":0,"ix":10},"p":{"a":0,"k":[277.798,308.804,0],"ix":2,"l":2},"a":{"a":0,"k":[0,0,0],"ix":1,"l":2},"s":{"a":0,"k":[100,100,100],"ix":6,"l":2}},"ao":0,"shapes":[{"ty":"gr","it":[{"ind":0,"ty":"sh","ix":1,"ks":{"a":0,"k":{"i":[[0,0],[0,0],[0,11.168],[43.081,0],[7.099,-2.126],[0,0]],"o":[[0,0],[4.228,-9.606],[0,-43.081],[-7.791,0],[0,0],[0,0]],"v":[[42.424,53.348],[43.615,54.695],[50.207,23.31],[-27.798,-54.695],[-50.207,-51.412],[-49.794,-50.945]],"c":true},"ix":2},"nm":"Path 1","mn":"ADBE Vector Shape - Group","hd":false},{"ty":"fl","c":{"a":0,"k":[1,0.78,0.22,1],"ix":4,"x":"var $bm_rt;\n$bm_rt = comp('wired-lineal-1780-medal-first-place').layer('control').effect('secondary')('Color');"},"o":{"a":0,"k":100,"ix":5},"r":1,"bm":0,"nm":".secondary","mn":"ADBE Vector Graphic - Fill","hd":false,"cl":"secondary"},{"ty":"tr","p":{"a":0,"k":[0,0],"ix":2},"a":{"a":0,"k":[0,0],"ix":1},"s":{"a":0,"k":[100,100],"ix":3},"r":{"a":0,"k":0,"ix":6},"o":{"a":0,"k":100,"ix":7},"sk":{"a":0,"k":0,"ix":4},"sa":{"a":0,"k":0,"ix":5},"nm":"Transform"}],"nm":"Group 1","np":2,"cix":2,"bm":1,"ix":1,"mn":"ADBE Vector Group","hd":false}],"ip":0,"op":844,"st":0,"ct":1,"bm":1},{"ddd":0,"ind":3,"ty":4,"nm":"Warstwa 2","parent":1,"sr":1,"ks":{"o":{"a":0,"k":50,"ix":11},"r":{"a":0,"k":0,"ix":10},"p":{"a":0,"k":[222.754,354.902,0],"ix":2,"l":2},"a":{"a":0,"k":[0,0,0],"ix":1,"l":2},"s":{"a":0,"k":[100,100,100],"ix":6,"l":2}},"ao":0,"shapes":[{"ty":"gr","it":[{"ind":0,"ty":"sh","ix":1,"ks":{"a":0,"k":{"i":[[0,0],[0,0],[0,-11.575],[-43.081,0],[-7.421,2.343],[0,0]],"o":[[0,0],[-4.523,9.878],[0,43.081],[8.195,0],[0,0],[0,0]],"v":[[-42.976,-54.404],[-43.695,-55.218],[-50.759,-22.788],[27.246,55.218],[50.759,51.604],[49.243,49.888]],"c":true},"ix":2},"nm":"Path 1","mn":"ADBE Vector Shape - Group","hd":false},{"ty":"fl","c":{"a":0,"k":[1,0.78,0.22,1],"ix":4,"x":"var $bm_rt;\n$bm_rt = comp('wired-lineal-1780-medal-first-place').layer('control').effect('secondary')('Color');"},"o":{"a":0,"k":100,"ix":5},"r":1,"bm":0,"nm":".secondary","mn":"ADBE Vector Graphic - Fill","hd":false,"cl":"secondary"},{"ty":"tr","p":{"a":0,"k":[0,0],"ix":2},"a":{"a":0,"k":[0,0],"ix":1},"s":{"a":0,"k":[100,100],"ix":3},"r":{"a":0,"k":0,"ix":6},"o":{"a":0,"k":100,"ix":7},"sk":{"a":0,"k":0,"ix":4},"sa":{"a":0,"k":0,"ix":5},"nm":"Transform"}],"nm":"Group 1","np":2,"cix":2,"bm":1,"ix":1,"mn":"ADBE Vector Group","hd":false}],"ip":0,"op":844,"st":0,"ct":1,"bm":1},{"ddd":0,"ind":4,"ty":4,"nm":"Warstwa 1","parent":1,"sr":1,"ks":{"o":{"a":0,"k":100,"ix":11},"r":{"a":0,"k":0,"ix":10},"p":{"a":0,"k":[250,332.114,0],"ix":2,"l":2},"a":{"a":0,"k":[0,0,0],"ix":1,"l":2},"s":{"a":0,"k":[100,100,100],"ix":6,"l":2}},"ao":0,"shapes":[{"ty":"gr","it":[{"ind":0,"ty":"sh","ix":1,"ks":{"a":0,"k":{"i":[[0,43.081],[-43.081,0],[0,-43.081],[43.081,0]],"o":[[0,-43.081],[43.081,0],[0,43.081],[-43.081,0]],"v":[[-78.005,0],[0,-78.005],[78.005,0],[0,78.005]],"c":true},"ix":2},"nm":"Path 1","mn":"ADBE Vector Shape - Group","hd":false},{"ty":"fl","c":{"a":0,"k":[1,0.78,0.22,1],"ix":4,"x":"var $bm_rt;\n$bm_rt = comp('wired-lineal-1780-medal-first-place').layer('control').effect('secondary')('Color');"},"o":{"a":0,"k":100,"ix":5},"r":1,"bm":0,"nm":".secondary","mn":"ADBE Vector Graphic - Fill","hd":false,"cl":"secondary"},{"ty":"tr","p":{"a":0,"k":[0,0],"ix":2},"a":{"a":0,"k":[0,0],"ix":1},"s":{"a":0,"k":[100,100],"ix":3},"r":{"a":0,"k":0,"ix":6},"o":{"a":0,"k":100,"ix":7},"sk":{"a":0,"k":0,"ix":4},"sa":{"a":0,"k":0,"ix":5},"nm":"Transform"}],"nm":"Group 1","np":2,"cix":2,"bm":0,"ix":1,"mn":"ADBE Vector Group","hd":false}],"ip":0,"op":844,"st":0,"ct":1,"bm":0},{"ddd":0,"ind":5,"ty":0,"nm":"ribbon 4","refId":"comp_3","sr":1,"ks":{"o":{"a":0,"k":100,"ix":11},"r":{"a":0,"k":0,"ix":10},"p":{"a":0,"k":[215,215,0],"ix":2,"l":2},"a":{"a":0,"k":[215,215,0],"ix":1,"l":2},"s":{"a":0,"k":[100,100,100],"ix":6,"l":2}},"ao":0,"w":430,"h":430,"ip":0,"op":844,"st":0,"bm":0}]},{"id":"comp_3","nm":"ribbon 4","fr":60,"layers":[{"ddd":0,"ind":1,"ty":4,"nm":"Ribbon 3","sr":1,"ks":{"o":{"a":0,"k":100,"ix":11},"r":{"a":0,"k":0,"ix":10},"p":{"a":0,"k":[215,161.627,0],"ix":2,"l":2},"a":{"a":0,"k":[250,196.627,0],"ix":1,"l":2},"s":{"a":0,"k":[100,100,100],"ix":6,"l":2}},"ao":0,"shapes":[{"ty":"gr","it":[{"ind":0,"ty":"sh","ix":1,"ks":{"a":1,"k":[{"i":{"x":0.015,"y":1},"o":{"x":0.167,"y":0.167},"t":0,"s":[{"i":[[0,0],[-27.916,-69.077]],"o":[[0,0],[0,0]],"v":[[-41.874,-103.615],[44.374,109.615]],"c":false}]},{"i":{"x":0.667,"y":1},"o":{"x":0.333,"y":0},"t":30,"s":[{"i":[[0,0],[12.864,-73.385]],"o":[[0,0],[0,0]],"v":[[-41.874,-103.615],[-28.418,115.055]],"c":false}]},{"i":{"x":0.667,"y":1},"o":{"x":0.333,"y":0},"t":50,"s":[{"i":[[0,0],[-50.502,-65.791]],"o":[[0,0],[0,0]],"v":[[-41.874,-103.615],[110.889,108.002]],"c":false}]},{"i":{"x":0.667,"y":1},"o":{"x":0.333,"y":0},"t":70,"s":[{"i":[[0,0],[-13.228,-70.258]],"o":[[0,0],[0,0]],"v":[[-41.874,-103.615],[29.473,112.151]],"c":false}]},{"i":{"x":0.667,"y":1},"o":{"x":0.333,"y":0},"t":92,"s":[{"i":[[0,0],[-23.878,-68.982]],"o":[[0,0],[0,0]],"v":[[-41.874,-103.615],[52.878,111.465]],"c":false}]},{"t":117,"s":[{"i":[[0,0],[-27.916,-69.077]],"o":[[0,0],[0,0]],"v":[[-41.874,-103.615],[44.374,110.115]],"c":false}]}],"ix":2},"nm":"Path 1","mn":"ADBE Vector Shape - Group","hd":false},{"ty":"st","c":{"a":0,"k":[0.071,0.075,0.192,1],"ix":3,"x":"var $bm_rt;\n$bm_rt = comp('wired-lineal-1780-medal-first-place').layer('control').effect('primary')('Color');"},"o":{"a":0,"k":100,"ix":4},"w":{"a":0,"k":7,"ix":5,"x":"var $bm_rt;\n$bm_rt = $bm_mul($bm_div(value, 2), comp('wired-lineal-1780-medal-first-place').layer('control').effect('stroke')('Menu'));"},"lc":2,"lj":2,"bm":0,"nm":".primary","mn":"ADBE Vector Graphic - Stroke","hd":false,"cl":"primary"},{"ty":"tr","p":{"a":0,"k":[206.13,193.496],"ix":2},"a":{"a":0,"k":[0,0],"ix":1},"s":{"a":0,"k":[100,100],"ix":3},"r":{"a":0,"k":0,"ix":6},"o":{"a":0,"k":100,"ix":7},"sk":{"a":0,"k":0,"ix":4},"sa":{"a":0,"k":0,"ix":5},"nm":"Transform"}],"nm":"Group 1","np":2,"cix":2,"bm":0,"ix":1,"mn":"ADBE Vector Group","hd":false},{"ty":"gr","it":[{"ty":"gr","it":[{"ind":0,"ty":"sh","ix":1,"ks":{"a":1,"k":[{"i":{"x":0.015,"y":1},"o":{"x":0.167,"y":0.167},"t":0,"s":[{"i":[[0,0],[0,0],[-26.976,-66.373],[-23.873,0.127]],"o":[[0,0],[0,0],[24.524,0.627],[-30.873,-75.873]],"v":[[-0.506,-106.746],[-85.903,-106.746],[0.506,106.746],[85.903,106.746]],"c":true}]},{"i":{"x":0.667,"y":1},"o":{"x":0.333,"y":0},"t":30,"s":[{"i":[[0,0],[0,0],[12.231,-70.594],[-20.324,-12.524]],"o":[[0,0],[0,0],[20.478,13.509],[13.951,-80.717]],"v":[[-0.506,-106.746],[-85.903,-106.746],[-64.961,90.293],[7.501,135.479]],"c":true}]},{"i":{"x":0.667,"y":1},"o":{"x":0.333,"y":0},"t":50,"s":[{"i":[[0,0],[0,0],[-48.671,-63.17],[-22.681,7.451]],"o":[[0,0],[0,0],[23.562,-6.839],[-55.671,-72.2]],"v":[[-0.506,-106.746],[-85.903,-106.746],[69.639,118.528],[150.93,92.364]],"c":true}]},{"i":{"x":0.667,"y":1},"o":{"x":0.333,"y":0},"t":70,"s":[{"i":[[0,0],[0,0],[-12.846,-67.537],[-21.295,-4.299]],"o":[[0,0],[0,0],[21.748,5.13],[-14.717,-77.21]],"v":[[-0.506,-106.746],[-85.903,-106.746],[-9.537,101.919],[66.56,117.726]],"c":true}]},{"i":{"x":0.667,"y":1},"o":{"x":0.333,"y":0},"t":92,"s":[{"i":[[0,0],[0,0],[-23.082,-66.289],[-21.691,-0.942]],"o":[[0,0],[0,0],[22.266,1.71],[-26.418,-75.779]],"v":[[-0.506,-106.746],[-85.903,-106.746],[13.085,106.664],[90.665,110.48]],"c":true}]},{"t":117,"s":[{"i":[[0,0],[0,0],[-26.976,-66.373],[-23.873,0.127]],"o":[[0,0],[0,0],[24.524,0.627],[-30.873,-75.873]],"v":[[-0.506,-106.746],[-85.903,-106.746],[0.506,106.746],[85.903,106.746]],"c":true}]}],"ix":2},"nm":"Path 1","mn":"ADBE Vector Shape - Group","hd":false},{"ty":"st","c":{"a":0,"k":[0.071,0.075,0.192,1],"ix":3,"x":"var $bm_rt;\n$bm_rt = comp('wired-lineal-1780-medal-first-place').layer('control').effect('primary')('Color');"},"o":{"a":0,"k":100,"ix":4},"w":{"a":0,"k":7,"ix":5,"x":"var $bm_rt;\n$bm_rt = $bm_mul($bm_div(value, 2), comp('wired-lineal-1780-medal-first-place').layer('control').effect('stroke')('Menu'));"},"lc":2,"lj":2,"bm":0,"nm":".primary","mn":"ADBE Vector Graphic - Stroke","hd":false,"cl":"primary"},{"ty":"tr","p":{"a":0,"k":[206.97,196.627],"ix":2},"a":{"a":0,"k":[0,0],"ix":1},"s":{"a":0,"k":[100,100],"ix":3},"r":{"a":0,"k":0,"ix":6},"o":{"a":0,"k":100,"ix":7},"sk":{"a":0,"k":0,"ix":4},"sa":{"a":0,"k":0,"ix":5},"nm":"Transform"}],"nm":"Group 1","np":3,"cix":2,"bm":0,"ix":1,"mn":"ADBE Vector Group","hd":false},{"ty":"tr","p":{"a":0,"k":[293.03,196.627],"ix":2},"a":{"a":0,"k":[293.03,196.627],"ix":1},"s":{"a":0,"k":[100,100],"ix":3},"r":{"a":0,"k":0,"ix":6},"o":{"a":0,"k":100,"ix":7},"sk":{"a":0,"k":0,"ix":4},"sa":{"a":0,"k":0,"ix":5},"nm":"Transform"}],"nm":"Group 2","np":2,"cix":2,"bm":0,"ix":2,"mn":"ADBE Vector Group","hd":false},{"ty":"tm","s":{"a":0,"k":0,"ix":1},"e":{"a":0,"k":100,"ix":2},"o":{"a":0,"k":0,"ix":3},"m":1,"ix":4,"nm":"Trim Paths 1","mn":"ADBE Vector Filter - Trim","hd":false}],"ip":0,"op":844,"st":0,"ct":1,"bm":0},{"ddd":0,"ind":2,"ty":4,"nm":"Warstwa 1 fill","sr":1,"ks":{"o":{"a":0,"k":100,"ix":11},"r":{"a":0,"k":0,"ix":10},"p":{"a":0,"k":[143.147,147.718,0],"ix":2,"l":2},"a":{"a":0,"k":[0,0,0],"ix":1,"l":2},"s":{"a":0,"k":[100,100,100],"ix":6,"l":2}},"ao":0,"shapes":[{"ty":"gr","it":[{"ind":0,"ty":"sh","ix":1,"ks":{"a":1,"k":[{"i":{"x":0,"y":1},"o":{"x":0.167,"y":0.167},"t":0,"s":[{"i":[[-10.843,-27.774],[-7.086,0.052],[4.025,9.238],[0,0]],"o":[[10.407,0.226],[-7.414,-17.802],[-5.975,0],[0,0]],"v":[[29.696,120.556],[72.517,120.834],[-14.172,-92.956],[-57.017,-92.837]],"c":true}]},{"i":{"x":0.833,"y":0.833},"o":{"x":0.335,"y":0},"t":30,"s":[{"i":[[10.782,-67.399],[-9.914,-6.552],[0,0],[0,0]],"o":[[3.282,3.101],[12.836,-71.302],[0,0],[0,0]],"v":[[-35.929,104.431],[-0.483,127.084],[-14.172,-92.956],[-57.017,-92.837]],"c":true}]},{"i":{"x":0.833,"y":0.833},"o":{"x":0.167,"y":0.167},"t":32,"s":[{"i":[[8.918,-69.208],[-10.594,-6.197],[0,0],[0.927,0]],"o":[[3.591,2.975],[11.293,-73.356],[0,0],[0.289,0.537]],"v":[[-32.235,104.994],[3.061,126.638],[-14.172,-92.956],[-57.017,-92.837]],"c":true}]},{"i":{"x":0.833,"y":0.833},"o":{"x":0.167,"y":0.167},"t":34,"s":[{"i":[[5.634,-72.393],[-11.792,-5.573],[0,0],[2.559,0]],"o":[[4.135,2.754],[5.796,-69.505],[0,0],[0.798,1.483]],"v":[[-22.281,106.675],[14.132,126.544],[-14.172,-92.956],[-57.017,-92.837]],"c":true}]},{"i":{"x":0.833,"y":0.833},"o":{"x":0.167,"y":0.167},"t":36,"s":[{"i":[[-3.187,-71.937],[-13.653,-4.604],[0,0],[5.094,0]],"o":[[4.98,2.411],[0.023,-72.98],[0,0],[1.589,2.952]],"v":[[-6.793,109.719],[29.331,125.762],[-14.172,-92.956],[-57.017,-92.837]],"c":true}]},{"i":{"x":0.833,"y":0.833},"o":{"x":0.167,"y":0.167},"t":37,"s":[{"i":[[-7.598,-71.709],[-14.584,-4.12],[0,0],[6.362,0]],"o":[[5.403,2.24],[-4.664,-66.836],[0,0],[1.984,3.686]],"v":[[1.701,111.991],[39.555,125.746],[-14.172,-92.956],[-57.017,-92.837]],"c":true}]},{"i":{"x":0.833,"y":0.833},"o":{"x":0.167,"y":0.167},"t":40,"s":[{"i":[[-20.83,-71.025],[-17.375,-2.666],[0,0],[10.164,0]],"o":[[6.67,1.725],[-15.125,-64.166],[0,0],[3.171,5.89]],"v":[[31.183,118.307],[69.478,123.948],[-14.172,-92.956],[-57.017,-92.837]],"c":true}]},{"i":{"x":0.833,"y":0.833},"o":{"x":0.167,"y":0.167},"t":43,"s":[{"i":[[-32.783,-69.311],[-14.312,0.653],[0,0],[13.868,0]],"o":[[8.522,0.45],[-25.712,-55.347],[0,0],[4.326,8.036]],"v":[[60.232,124.132],[100.315,122.379],[-14.172,-92.956],[-57.017,-92.837]],"c":true}]},{"i":{"x":0.634,"y":1},"o":{"x":0.167,"y":0.167},"t":45,"s":[{"i":[[-40.751,-68.168],[-12.27,2.867],[0,0],[16.338,0]],"o":[[9.756,-0.4],[-28.77,-49.633],[0,0],[5.096,9.467]],"v":[[77.097,127.182],[117.123,120.915],[-14.172,-92.956],[-57.017,-92.837]],"c":true}]},{"i":{"x":0.65,"y":1},"o":{"x":0.351,"y":0},"t":50,"s":[{"i":[[-51.343,-66.649],[-14.164,4.198],[0,0],[19.62,0]],"o":[[4.157,-1.024],[-30.289,-40.052],[0,0],[6.12,11.369]],"v":[[98.446,132.181],[139.392,119.584],[-14.172,-92.956],[-57.017,-92.837]],"c":true}]},{"i":{"x":0.647,"y":1},"o":{"x":0.352,"y":0},"t":70,"s":[{"i":[[-3.968,-38.024],[-13.164,-2.927],[0,0],[19.62,0]],"o":[[6.782,1.351],[-11.164,-67.302],[0,0],[7.87,14.119]],"v":[[19.321,115.806],[57.517,124.084],[-14.172,-92.956],[-57.017,-92.837]],"c":true}]},{"i":{"x":0.667,"y":1},"o":{"x":0.372,"y":0},"t":92,"s":[{"i":[[-11.468,-40.774],[-14.414,-0.802],[0,0],[19.62,0]],"o":[[8.032,0.726],[-22.914,-69.802],[0,0],[7.87,14.119]],"v":[[41.571,120.556],[80.767,122.584],[-14.172,-92.956],[-57.017,-92.837]],"c":true}]},{"t":117,"s":[{"i":[[-15.968,-40.524],[-14.664,0.073],[0,0],[19.62,0]],"o":[[9.157,0.226],[-28.289,-70.552],[0,0],[5.87,12.119]],"v":[[28.821,120.556],[72.142,120.834],[-14.172,-92.956],[-57.017,-92.837]],"c":true}]}],"ix":2},"nm":"Path 1","mn":"ADBE Vector Shape - Group","hd":false},{"ty":"fl","c":{"a":0,"k":[0.443,0.4,0.933,1],"ix":4,"x":"var $bm_rt;\n$bm_rt = comp('wired-lineal-1780-medal-first-place').layer('control').effect('quaternary')('Color');"},"o":{"a":0,"k":100,"ix":5},"r":1,"bm":0,"nm":".quaternary","mn":"ADBE Vector Graphic - Fill","hd":false,"cl":"quaternary"},{"ty":"tr","p":{"a":0,"k":[0,0],"ix":2},"a":{"a":0,"k":[0,0],"ix":1},"s":{"a":0,"k":[100,100],"ix":3},"r":{"a":0,"k":0,"ix":6},"o":{"a":0,"k":100,"ix":7},"sk":{"a":0,"k":0,"ix":4},"sa":{"a":0,"k":0,"ix":5},"nm":"Transform"}],"nm":"Group 1","np":2,"cix":2,"bm":0,"ix":1,"mn":"ADBE Vector Group","hd":false}],"ip":0,"op":844,"st":0,"ct":1,"bm":0},{"ddd":0,"ind":3,"ty":4,"nm":"Ribbon fill","sr":1,"ks":{"o":{"a":0,"k":100,"ix":11},"r":{"a":0,"k":0,"ix":10},"p":{"a":0,"k":[215,161.627,0],"ix":2,"l":2},"a":{"a":0,"k":[250,196.627,0],"ix":1,"l":2},"s":{"a":0,"k":[100,100,100],"ix":6,"l":2}},"ao":0,"shapes":[{"ty":"gr","it":[{"ty":"gr","it":[{"ind":0,"ty":"sh","ix":1,"ks":{"a":1,"k":[{"i":{"x":0.015,"y":1},"o":{"x":0.167,"y":0.167},"t":0,"s":[{"i":[[0,0],[-26.976,-66.373],[-23.873,0.127],[0,0]],"o":[[0,0],[24.524,0.627],[-30.873,-75.873],[0,0]],"v":[[-85.903,-106.746],[0.506,106.746],[85.903,106.746],[-0.506,-106.746]],"c":false}]},{"i":{"x":0.667,"y":1},"o":{"x":0.333,"y":0},"t":30,"s":[{"i":[[0,0],[12.231,-70.594],[-20.324,-12.524],[0,0]],"o":[[0,0],[20.478,13.509],[13.951,-80.717],[0,0]],"v":[[-85.903,-106.746],[-64.961,90.293],[7.501,135.479],[-0.506,-106.746]],"c":false}]},{"i":{"x":0.667,"y":1},"o":{"x":0.333,"y":0},"t":50,"s":[{"i":[[0,0],[-48.671,-63.17],[-22.681,7.451],[0,0]],"o":[[0,0],[23.562,-6.839],[-55.671,-72.2],[0,0]],"v":[[-85.903,-106.746],[69.639,118.528],[150.93,92.364],[-0.506,-106.746]],"c":false}]},{"i":{"x":0.667,"y":1},"o":{"x":0.333,"y":0},"t":70,"s":[{"i":[[0,0],[-12.846,-67.537],[-21.295,-4.299],[0,0]],"o":[[0,0],[21.748,5.13],[-14.717,-77.21],[0,0]],"v":[[-85.903,-106.746],[-9.537,101.919],[66.56,117.726],[-0.506,-106.746]],"c":false}]},{"i":{"x":0.667,"y":1},"o":{"x":0.333,"y":0},"t":92,"s":[{"i":[[0,0],[-23.082,-66.289],[-21.691,-0.942],[0,0]],"o":[[0,0],[22.266,1.71],[-26.418,-75.779],[0,0]],"v":[[-85.903,-106.746],[13.085,106.664],[90.665,110.48],[-0.506,-106.746]],"c":false}]},{"t":117,"s":[{"i":[[0,0],[-26.976,-66.373],[-23.873,0.127],[0,0]],"o":[[0,0],[24.524,0.627],[-30.873,-75.873],[0,0]],"v":[[-85.903,-106.746],[0.506,106.746],[85.903,106.746],[-0.506,-106.746]],"c":false}]}],"ix":2},"nm":"Path 1","mn":"ADBE Vector Shape - Group","hd":false},{"ty":"st","c":{"a":0,"k":[0.071,0.075,0.192,1],"ix":3,"x":"var $bm_rt;\n$bm_rt = comp('wired-lineal-1780-medal-first-place').layer('control').effect('primary')('Color');"},"o":{"a":0,"k":100,"ix":4},"w":{"a":0,"k":0,"ix":5,"x":"var $bm_rt;\n$bm_rt = $bm_mul($bm_div(value, 2), comp('wired-lineal-1780-medal-first-place').layer('control').effect('stroke')('Menu'));"},"lc":2,"lj":2,"bm":0,"nm":".primary","mn":"ADBE Vector Graphic - Stroke","hd":false,"cl":"primary"},{"ty":"fl","c":{"a":0,"k":[0.922,0.902,0.937,1],"ix":4,"x":"var $bm_rt;\n$bm_rt = comp('wired-lineal-1780-medal-first-place').layer('control').effect('tertiary')('Color');"},"o":{"a":0,"k":100,"ix":5},"r":1,"bm":0,"nm":".tertiary","mn":"ADBE Vector Graphic - Fill","hd":false,"cl":"tertiary"},{"ty":"tr","p":{"a":0,"k":[206.97,196.627],"ix":2},"a":{"a":0,"k":[0,0],"ix":1},"s":{"a":0,"k":[100,100],"ix":3},"r":{"a":0,"k":0,"ix":6},"o":{"a":0,"k":100,"ix":7},"sk":{"a":0,"k":0,"ix":4},"sa":{"a":0,"k":0,"ix":5},"nm":"Transform"}],"nm":"Group 1","np":3,"cix":2,"bm":0,"ix":1,"mn":"ADBE Vector Group","hd":false},{"ty":"gr","it":[{"ind":0,"ty":"sh","ix":1,"ks":{"a":1,"k":[{"i":{"x":0.015,"y":1},"o":{"x":0.167,"y":0.167},"t":0,"s":[{"i":[[0,0],[26.976,-68.373],[0,0],[0,0]],"o":[[0,0],[-33.524,0.127],[0,0],[0,0]],"v":[[85.903,-106.746],[-0.506,106.746],[-85.903,106.746],[0.506,-106.746]],"c":false}]},{"i":{"x":0.667,"y":1},"o":{"x":0.333,"y":0},"t":30,"s":[{"i":[[0,0],[55.825,-52.422],[18.787,11.765],[0,0]],"o":[[0,0],[-28.513,-17.631],[64.287,-55.735],[0,0]],"v":[[85.903,-106.746],[-78.855,135.295],[-151.317,90.108],[0.506,-106.746]],"c":false}]},{"i":{"x":0.667,"y":1},"o":{"x":0.333,"y":0},"t":50,"s":[{"i":[[0,0],[1.994,-81.852],[0,0],[0,0]],"o":[[0,0],[-31.868,10.408],[0,0],[0,0]],"v":[[85.903,-106.746],[64.538,92.47],[-16.752,118.635],[0.506,-106.746]],"c":false}]},{"i":{"x":0.667,"y":1},"o":{"x":0.333,"y":0},"t":70,"s":[{"i":[[0,0],[35.568,-59.435],[0,0],[0,0]],"o":[[0,0],[-29.895,-6.086],[0,0],[0,0]],"v":[[85.903,-106.746],[-19.811,117.661],[-95.908,101.854],[0.506,-106.746]],"c":false}]},{"i":{"x":0.667,"y":1},"o":{"x":0.333,"y":0},"t":92,"s":[{"i":[[0,0],[25.975,-65.84],[0,0],[0,0]],"o":[[0,0],[-30.458,-1.373],[0,0],[0,0]],"v":[[85.903,-106.746],[4.289,110.464],[-73.292,106.649],[0.506,-106.746]],"c":false}]},{"t":117,"s":[{"i":[[0,0],[26.976,-68.373],[0,0],[0,0]],"o":[[0,0],[-33.524,0.127],[0,0],[0,0]],"v":[[85.903,-106.746],[-0.506,106.746],[-85.903,106.746],[0.506,-106.746]],"c":false}]}],"ix":2},"nm":"Path 1","mn":"ADBE Vector Shape - Group","hd":false},{"ty":"st","c":{"a":0,"k":[0.071,0.075,0.192,1],"ix":3,"x":"var $bm_rt;\n$bm_rt = comp('wired-lineal-1780-medal-first-place').layer('control').effect('primary')('Color');"},"o":{"a":0,"k":100,"ix":4},"w":{"a":0,"k":0,"ix":5,"x":"var $bm_rt;\n$bm_rt = $bm_mul($bm_div(value, 2), comp('wired-lineal-1780-medal-first-place').layer('control').effect('stroke')('Menu'));"},"lc":2,"lj":2,"bm":0,"nm":".primary","mn":"ADBE Vector Graphic - Stroke","hd":false,"cl":"primary"},{"ty":"tr","p":{"a":0,"k":[293.03,196.627],"ix":2},"a":{"a":0,"k":[0,0],"ix":1},"s":{"a":0,"k":[100,100],"ix":3},"r":{"a":0,"k":0,"ix":6},"o":{"a":0,"k":100,"ix":7},"sk":{"a":0,"k":0,"ix":4},"sa":{"a":0,"k":0,"ix":5},"nm":"Transform"}],"nm":"Group 2","np":2,"cix":2,"bm":0,"ix":2,"mn":"ADBE Vector Group","hd":false},{"ty":"tr","p":{"a":0,"k":[293.03,196.627],"ix":2},"a":{"a":0,"k":[293.03,196.627],"ix":1},"s":{"a":0,"k":[100,100],"ix":3},"r":{"a":0,"k":0,"ix":6},"o":{"a":0,"k":100,"ix":7},"sk":{"a":0,"k":0,"ix":4},"sa":{"a":0,"k":0,"ix":5},"nm":"Transform"}],"nm":"Group 2","np":2,"cix":2,"bm":0,"ix":1,"mn":"ADBE Vector Group","hd":false}],"ip":0,"op":844,"st":0,"ct":1,"bm":0},{"ddd":0,"ind":4,"ty":4,"nm":"Ribbon 2","sr":1,"ks":{"o":{"a":0,"k":100,"ix":11},"r":{"a":0,"k":0,"ix":10},"p":{"a":0,"k":[215,161.627,0],"ix":2,"l":2},"a":{"a":0,"k":[250,196.627,0],"ix":1,"l":2},"s":{"a":0,"k":[100,100,100],"ix":6,"l":2}},"ao":0,"shapes":[{"ty":"gr","it":[{"ty":"gr","it":[{"ind":0,"ty":"sh","ix":1,"ks":{"a":1,"k":[{"i":{"x":0.015,"y":1},"o":{"x":0.167,"y":0.167},"t":0,"s":[{"i":[[0,0],[0,0],[0,0],[-33.524,0.127]],"o":[[0,0],[0,0],[0,0],[26.976,-68.373]],"v":[[85.903,-106.746],[0.506,-106.746],[-85.903,106.746],[-0.506,106.746]],"c":true}]},{"i":{"x":0.667,"y":1},"o":{"x":0.333,"y":0},"t":30,"s":[{"i":[[0,0],[0,0],[64.287,-55.735],[-28.513,-17.631]],"o":[[0,0],[0,0],[18.787,11.765],[55.825,-52.422]],"v":[[85.903,-106.746],[0.506,-106.746],[-151.317,90.108],[-78.855,135.295]],"c":true}]},{"i":{"x":0.667,"y":1},"o":{"x":0.333,"y":0},"t":50,"s":[{"i":[[0,0],[0,0],[0,0],[-31.868,10.408]],"o":[[0,0],[0,0],[0,0],[1.994,-81.852]],"v":[[85.903,-106.746],[0.506,-106.746],[-16.752,118.635],[64.538,92.47]],"c":true}]},{"i":{"x":0.667,"y":1},"o":{"x":0.333,"y":0},"t":70,"s":[{"i":[[0,0],[0,0],[0,0],[-29.895,-6.086]],"o":[[0,0],[0,0],[0,0],[35.568,-59.435]],"v":[[85.903,-106.746],[0.506,-106.746],[-95.908,101.854],[-19.811,117.661]],"c":true}]},{"i":{"x":0.667,"y":1},"o":{"x":0.333,"y":0},"t":92,"s":[{"i":[[0,0],[0,0],[0,0],[-30.458,-1.373]],"o":[[0,0],[0,0],[0,0],[25.975,-65.84]],"v":[[85.903,-106.746],[0.506,-106.746],[-73.292,106.649],[4.289,110.464]],"c":true}]},{"t":117,"s":[{"i":[[0,0],[0,0],[0,0],[-33.524,0.127]],"o":[[0,0],[0,0],[0,0],[26.976,-68.373]],"v":[[85.903,-106.746],[0.506,-106.746],[-85.903,106.746],[-0.506,106.746]],"c":true}]}],"ix":2},"nm":"Path 1","mn":"ADBE Vector Shape - Group","hd":false},{"ty":"st","c":{"a":0,"k":[0.071,0.075,0.192,1],"ix":3,"x":"var $bm_rt;\n$bm_rt = comp('wired-lineal-1780-medal-first-place').layer('control').effect('primary')('Color');"},"o":{"a":0,"k":100,"ix":4},"w":{"a":0,"k":7,"ix":5,"x":"var $bm_rt;\n$bm_rt = $bm_mul($bm_div(value, 2), comp('wired-lineal-1780-medal-first-place').layer('control').effect('stroke')('Menu'));"},"lc":2,"lj":2,"bm":0,"nm":".primary","mn":"ADBE Vector Graphic - Stroke","hd":false,"cl":"primary"},{"ty":"tr","p":{"a":0,"k":[293.03,196.627],"ix":2},"a":{"a":0,"k":[0,0],"ix":1},"s":{"a":0,"k":[100,100],"ix":3},"r":{"a":0,"k":0,"ix":6},"o":{"a":0,"k":100,"ix":7},"sk":{"a":0,"k":0,"ix":4},"sa":{"a":0,"k":0,"ix":5},"nm":"Transform"}],"nm":"Group 2","np":2,"cix":2,"bm":0,"ix":1,"mn":"ADBE Vector Group","hd":false},{"ty":"tr","p":{"a":0,"k":[293.03,196.627],"ix":2},"a":{"a":0,"k":[293.03,196.627],"ix":1},"s":{"a":0,"k":[100,100],"ix":3},"r":{"a":0,"k":0,"ix":6},"o":{"a":0,"k":100,"ix":7},"sk":{"a":0,"k":0,"ix":4},"sa":{"a":0,"k":0,"ix":5},"nm":"Transform"}],"nm":"Group 2","np":1,"cix":2,"bm":0,"ix":1,"mn":"ADBE Vector Group","hd":false},{"ty":"gr","it":[{"ind":0,"ty":"sh","ix":1,"ks":{"a":1,"k":[{"i":{"x":0.015,"y":1},"o":{"x":0.167,"y":0.167},"t":0,"s":[{"i":[[0,0],[27.916,-69.077]],"o":[[0,0],[0,0]],"v":[[41.874,-103.615],[-41.874,103.615]],"c":false}]},{"i":{"x":0.667,"y":1},"o":{"x":0.333,"y":0},"t":30,"s":[{"i":[[0,0],[60.239,-43.842]],"o":[[0,0],[0,0]],"v":[[41.874,-103.615],[-110.857,111.408]],"c":false}]},{"i":{"x":0.667,"y":1},"o":{"x":0.333,"y":0},"t":50,"s":[{"i":[[0,0],[2.645,-82.897]],"o":[[0,0],[0,0]],"v":[[41.874,-103.615],[23.066,101.425]],"c":false}]},{"i":{"x":0.667,"y":1},"o":{"x":0.333,"y":0},"t":70,"s":[{"i":[[0,0],[36.524,-59.924]],"o":[[0,0],[0,0]],"v":[[41.874,-103.615],[-55.712,107.298]],"c":false}]},{"i":{"x":0.667,"y":1},"o":{"x":0.333,"y":0},"t":92,"s":[{"i":[[0,0],[26.844,-66.488]],"o":[[0,0],[0,0]],"v":[[41.874,-103.615],[-33.204,105.62]],"c":false}]},{"t":117,"s":[{"i":[[0,0],[27.916,-69.077]],"o":[[0,0],[0,0]],"v":[[41.874,-103.615],[-41.874,103.615]],"c":false}]}],"ix":2},"nm":"Path 1","mn":"ADBE Vector Shape - Group","hd":false},{"ty":"st","c":{"a":0,"k":[0.071,0.075,0.192,1],"ix":3,"x":"var $bm_rt;\n$bm_rt = comp('wired-lineal-1780-medal-first-place').layer('control').effect('primary')('Color');"},"o":{"a":0,"k":100,"ix":4},"w":{"a":0,"k":7,"ix":5,"x":"var $bm_rt;\n$bm_rt = $bm_mul($bm_div(value, 2), comp('wired-lineal-1780-medal-first-place').layer('control').effect('stroke')('Menu'));"},"lc":2,"lj":2,"bm":0,"nm":".primary","mn":"ADBE Vector Graphic - Stroke","hd":false,"cl":"primary"},{"ty":"tr","p":{"a":0,"k":[293.461,193.776],"ix":2},"a":{"a":0,"k":[0,0],"ix":1},"s":{"a":0,"k":[100,100],"ix":3},"r":{"a":0,"k":0,"ix":6},"o":{"a":0,"k":100,"ix":7},"sk":{"a":0,"k":0,"ix":4},"sa":{"a":0,"k":0,"ix":5},"nm":"Transform"}],"nm":"Group 3","np":2,"cix":2,"bm":0,"ix":2,"mn":"ADBE Vector Group","hd":false}],"ip":0,"op":844,"st":0,"ct":1,"bm":0},{"ddd":0,"ind":5,"ty":4,"nm":"mask","td":1,"sr":1,"ks":{"o":{"a":0,"k":100,"ix":11},"r":{"a":0,"k":0,"ix":10},"p":{"a":0,"k":[215,161.627,0],"ix":2,"l":2},"a":{"a":0,"k":[250,196.627,0],"ix":1,"l":2},"s":{"a":0,"k":[100,100,100],"ix":6,"l":2}},"ao":0,"shapes":[{"ty":"gr","it":[{"ty":"gr","it":[{"ind":0,"ty":"sh","ix":1,"ks":{"a":1,"k":[{"i":{"x":0.015,"y":1},"o":{"x":0.167,"y":0.167},"t":0,"s":[{"i":[[0,0],[26.976,-68.373],[0,0],[0,0]],"o":[[0,0],[-33.524,0.127],[0,0],[0,0]],"v":[[85.903,-106.746],[-0.506,106.746],[-85.903,106.746],[0.506,-106.746]],"c":false}]},{"i":{"x":0.667,"y":1},"o":{"x":0.333,"y":0},"t":30,"s":[{"i":[[0,0],[55.825,-52.422],[18.787,11.765],[0,0]],"o":[[0,0],[-28.513,-17.631],[64.287,-55.735],[0,0]],"v":[[85.903,-106.746],[-78.855,135.295],[-151.317,90.108],[0.506,-106.746]],"c":false}]},{"i":{"x":0.667,"y":1},"o":{"x":0.333,"y":0},"t":50,"s":[{"i":[[0,0],[1.994,-81.852],[0,0],[0,0]],"o":[[0,0],[-31.868,10.408],[0,0],[0,0]],"v":[[85.903,-106.746],[64.538,92.47],[-16.752,118.635],[0.506,-106.746]],"c":false}]},{"i":{"x":0.667,"y":1},"o":{"x":0.333,"y":0},"t":70,"s":[{"i":[[0,0],[35.568,-59.435],[0,0],[0,0]],"o":[[0,0],[-29.895,-6.086],[0,0],[0,0]],"v":[[85.903,-106.746],[-19.811,117.661],[-95.908,101.854],[0.506,-106.746]],"c":false}]},{"i":{"x":0.667,"y":1},"o":{"x":0.333,"y":0},"t":92,"s":[{"i":[[0,0],[25.975,-65.84],[0,0],[0,0]],"o":[[0,0],[-30.458,-1.373],[0,0],[0,0]],"v":[[85.903,-106.746],[4.289,110.464],[-73.292,106.649],[0.506,-106.746]],"c":false}]},{"t":117,"s":[{"i":[[0,0],[26.976,-68.373],[0,0],[0,0]],"o":[[0,0],[-33.524,0.127],[0,0],[0,0]],"v":[[85.903,-106.746],[-0.506,106.746],[-85.903,106.746],[0.506,-106.746]],"c":false}]}],"ix":2},"nm":"Path 1","mn":"ADBE Vector Shape - Group","hd":false},{"ty":"fl","c":{"a":0,"k":[0.921568632126,0.901960790157,0.937254905701,1],"ix":4},"o":{"a":0,"k":100,"ix":5},"r":1,"bm":0,"nm":"Fill 1","mn":"ADBE Vector Graphic - Fill","hd":false},{"ty":"tr","p":{"a":0,"k":[293.03,196.627],"ix":2},"a":{"a":0,"k":[0,0],"ix":1},"s":{"a":0,"k":[100,100],"ix":3},"r":{"a":0,"k":0,"ix":6},"o":{"a":0,"k":100,"ix":7},"sk":{"a":0,"k":0,"ix":4},"sa":{"a":0,"k":0,"ix":5},"nm":"Transform"}],"nm":"Group 2","np":2,"cix":2,"bm":0,"ix":1,"mn":"ADBE Vector Group","hd":false},{"ty":"tr","p":{"a":0,"k":[293.03,196.627],"ix":2},"a":{"a":0,"k":[293.03,196.627],"ix":1},"s":{"a":0,"k":[100,100],"ix":3},"r":{"a":0,"k":0,"ix":6},"o":{"a":0,"k":100,"ix":7},"sk":{"a":0,"k":0,"ix":4},"sa":{"a":0,"k":0,"ix":5},"nm":"Transform"}],"nm":"Group 2","np":1,"cix":2,"bm":0,"ix":1,"mn":"ADBE Vector Group","hd":false}],"ip":0,"op":844,"st":0,"ct":1,"bm":0},{"ddd":0,"ind":6,"ty":4,"nm":"shadow","tt":1,"tp":5,"sr":1,"ks":{"o":{"a":0,"k":50,"ix":11},"r":{"a":0,"k":0,"ix":10},"p":{"a":0,"k":[229,161.627,0],"ix":2,"l":2},"a":{"a":0,"k":[250,196.627,0],"ix":1,"l":2},"s":{"a":0,"k":[100,100,100],"ix":6,"l":2}},"ao":0,"shapes":[{"ty":"gr","it":[{"ty":"gr","it":[{"ind":0,"ty":"sh","ix":1,"ks":{"a":1,"k":[{"i":{"x":0.015,"y":1},"o":{"x":0.167,"y":0.167},"t":0,"s":[{"i":[[0,0],[-26.976,-66.373],[-23.873,0.127],[0,0],[0,0]],"o":[[0,0],[24.524,0.627],[-30.873,-75.873],[0,0],[0,0]],"v":[[-85.903,-106.746],[0.506,106.746],[85.903,106.746],[57.494,36.254],[48.53,56.873]],"c":false}]},{"i":{"x":0.667,"y":1},"o":{"x":0.333,"y":0},"t":30,"s":[{"i":[[0,0],[12.231,-70.594],[-20.324,-12.524],[0,0],[0,0]],"o":[[0,0],[20.478,13.509],[13.951,-80.717],[0,0],[0,0]],"v":[[-85.903,-106.746],[-64.961,90.293],[7.501,135.479],[12.994,54.254],[-4.892,76.741]],"c":false}]},{"i":{"x":0.667,"y":1},"o":{"x":0.333,"y":0},"t":50,"s":[{"i":[[0,0],[-48.671,-63.17],[-22.681,7.451],[0,0],[0,0]],"o":[[0,0],[23.562,-6.839],[-55.671,-72.2],[0,0],[0,0]],"v":[[-85.903,-106.746],[69.639,118.528],[150.93,92.364],[100.744,25.004],[98.68,56.053]],"c":false}]},{"i":{"x":0.667,"y":1},"o":{"x":0.333,"y":0},"t":70,"s":[{"i":[[0,0],[-12.846,-67.537],[-21.295,-4.299],[0,0],[0,0]],"o":[[0,0],[21.748,5.13],[-14.717,-77.21],[0,0],[0,0]],"v":[[-85.903,-106.746],[-9.537,101.919],[66.56,117.726],[49.244,42.254],[38.091,64.868]],"c":false}]},{"i":{"x":0.667,"y":1},"o":{"x":0.333,"y":0},"t":92,"s":[{"i":[[0,0],[-23.082,-66.289],[-21.691,-0.942],[0,0],[0,0]],"o":[[0,0],[22.266,1.71],[-26.418,-75.779],[0,0],[0,0]],"v":[[-85.903,-106.746],[13.085,106.664],[90.665,110.48],[63.244,38.254],[54.862,61.238]],"c":false}]},{"t":117,"s":[{"i":[[0,0],[-26.976,-66.373],[-23.873,0.127],[0,0],[0,0]],"o":[[0,0],[24.524,0.627],[-30.873,-75.873],[0,0],[0,0]],"v":[[-85.903,-106.746],[0.506,106.746],[85.903,106.746],[56.494,35.754],[48.368,56.124]],"c":false}]}],"ix":2},"nm":"Path 1","mn":"ADBE Vector Shape - Group","hd":false},{"ty":"fl","c":{"a":0,"k":[0.443,0.4,0.933,1],"ix":4,"x":"var $bm_rt;\n$bm_rt = comp('wired-lineal-1780-medal-first-place').layer('control').effect('quaternary')('Color');"},"o":{"a":0,"k":100,"ix":5},"r":1,"bm":0,"nm":".quaternary","mn":"ADBE Vector Graphic - Fill","hd":false,"cl":"quaternary"},{"ty":"tr","p":{"a":0,"k":[206.97,196.627],"ix":2},"a":{"a":0,"k":[0,0],"ix":1},"s":{"a":0,"k":[100,100],"ix":3},"r":{"a":0,"k":0,"ix":6},"o":{"a":0,"k":100,"ix":7},"sk":{"a":0,"k":0,"ix":4},"sa":{"a":0,"k":0,"ix":5},"nm":"Transform"}],"nm":"Group 1","np":2,"cix":2,"bm":0,"ix":1,"mn":"ADBE Vector Group","hd":false},{"ty":"tr","p":{"a":0,"k":[293.03,196.627],"ix":2},"a":{"a":0,"k":[293.03,196.627],"ix":1},"s":{"a":0,"k":[100,100],"ix":3},"r":{"a":0,"k":0,"ix":6},"o":{"a":0,"k":100,"ix":7},"sk":{"a":0,"k":0,"ix":4},"sa":{"a":0,"k":0,"ix":5},"nm":"Transform"}],"nm":"Group 2","np":1,"cix":2,"bm":0,"ix":1,"mn":"ADBE Vector Group","hd":false}],"ip":0,"op":844,"st":0,"ct":1,"bm":1},{"ddd":0,"ind":7,"ty":4,"nm":"mask 2","td":1,"sr":1,"ks":{"o":{"a":0,"k":100,"ix":11},"r":{"a":0,"k":0,"ix":10},"p":{"a":0,"k":[215,161.627,0],"ix":2,"l":2},"a":{"a":0,"k":[250,196.627,0],"ix":1,"l":2},"s":{"a":0,"k":[100,100,100],"ix":6,"l":2}},"ao":0,"shapes":[{"ty":"gr","it":[{"ty":"gr","it":[{"ind":0,"ty":"sh","ix":1,"ks":{"a":1,"k":[{"i":{"x":0.015,"y":1},"o":{"x":0.167,"y":0.167},"t":0,"s":[{"i":[[0,0],[26.976,-68.373],[0,0],[0,0]],"o":[[0,0],[-33.524,0.127],[0,0],[0,0]],"v":[[85.903,-106.746],[-0.506,106.746],[-85.903,106.746],[0.506,-106.746]],"c":false}]},{"i":{"x":0.667,"y":1},"o":{"x":0.333,"y":0},"t":30,"s":[{"i":[[0,0],[55.825,-52.422],[18.787,11.765],[0,0]],"o":[[0,0],[-28.513,-17.631],[64.287,-55.735],[0,0]],"v":[[85.903,-106.746],[-78.855,135.295],[-151.317,90.108],[0.506,-106.746]],"c":false}]},{"i":{"x":0.667,"y":1},"o":{"x":0.333,"y":0},"t":50,"s":[{"i":[[0,0],[1.994,-81.852],[0,0],[0,0]],"o":[[0,0],[-31.868,10.408],[0,0],[0,0]],"v":[[85.903,-106.746],[64.538,92.47],[-16.752,118.635],[0.506,-106.746]],"c":false}]},{"i":{"x":0.667,"y":1},"o":{"x":0.333,"y":0},"t":70,"s":[{"i":[[0,0],[35.568,-59.435],[0,0],[0,0]],"o":[[0,0],[-29.895,-6.086],[0,0],[0,0]],"v":[[85.903,-106.746],[-19.811,117.661],[-95.908,101.854],[0.506,-106.746]],"c":false}]},{"i":{"x":0.667,"y":1},"o":{"x":0.333,"y":0},"t":92,"s":[{"i":[[0,0],[25.975,-65.84],[0,0],[0,0]],"o":[[0,0],[-30.458,-1.373],[0,0],[0,0]],"v":[[85.903,-106.746],[4.289,110.464],[-73.292,106.649],[0.506,-106.746]],"c":false}]},{"t":117,"s":[{"i":[[0,0],[26.976,-68.373],[0,0],[0,0]],"o":[[0,0],[-33.524,0.127],[0,0],[0,0]],"v":[[85.903,-106.746],[-0.506,106.746],[-85.903,106.746],[0.506,-106.746]],"c":false}]}],"ix":2},"nm":"Path 1","mn":"ADBE Vector Shape - Group","hd":false},{"ty":"fl","c":{"a":0,"k":[0.921568632126,0.901960790157,0.937254905701,1],"ix":4},"o":{"a":0,"k":100,"ix":5},"r":1,"bm":0,"nm":"Fill 1","mn":"ADBE Vector Graphic - Fill","hd":false},{"ty":"tr","p":{"a":0,"k":[293.03,196.627],"ix":2},"a":{"a":0,"k":[0,0],"ix":1},"s":{"a":0,"k":[100,100],"ix":3},"r":{"a":0,"k":0,"ix":6},"o":{"a":0,"k":100,"ix":7},"sk":{"a":0,"k":0,"ix":4},"sa":{"a":0,"k":0,"ix":5},"nm":"Transform"}],"nm":"Group 2","np":2,"cix":2,"bm":0,"ix":1,"mn":"ADBE Vector Group","hd":false},{"ty":"tr","p":{"a":0,"k":[293.03,196.627],"ix":2},"a":{"a":0,"k":[293.03,196.627],"ix":1},"s":{"a":0,"k":[100,100],"ix":3},"r":{"a":0,"k":0,"ix":6},"o":{"a":0,"k":100,"ix":7},"sk":{"a":0,"k":0,"ix":4},"sa":{"a":0,"k":0,"ix":5},"nm":"Transform"}],"nm":"Group 2","np":1,"cix":2,"bm":0,"ix":1,"mn":"ADBE Vector Group","hd":false}],"ip":0,"op":844,"st":0,"ct":1,"bm":0},{"ddd":0,"ind":8,"ty":4,"nm":"shadow 2","tt":1,"tp":7,"sr":1,"ks":{"o":{"a":0,"k":50,"ix":11},"r":{"a":0,"k":0,"ix":10},"p":{"a":0,"k":[229,161.627,0],"ix":2,"l":2},"a":{"a":0,"k":[250,196.627,0],"ix":1,"l":2},"s":{"a":0,"k":[100,100,100],"ix":6,"l":2}},"ao":0,"shapes":[{"ty":"gr","it":[{"ty":"gr","it":[{"ind":0,"ty":"sh","ix":1,"ks":{"a":1,"k":[{"i":{"x":0.015,"y":1},"o":{"x":0.167,"y":0.167},"t":0,"s":[{"i":[[0,0],[0,0],[0,0],[0,0]],"o":[[0,0],[0,0],[0,0],[0,0]],"v":[[-85.903,-106.746],[25.506,106.246],[57.228,36.441],[-0.506,-106.746]],"c":false}]},{"i":{"x":0.667,"y":1},"o":{"x":0.333,"y":0},"t":30,"s":[{"i":[[0,0],[12.231,-70.594],[0,0],[0,0]],"o":[[0,0],[20.478,13.509],[0,0],[0,0]],"v":[[-85.903,-106.746],[-51.961,100.293],[14.178,53.447],[-0.506,-106.746]],"c":false}]},{"i":{"x":0.667,"y":1},"o":{"x":0.333,"y":0},"t":50,"s":[{"i":[[0,0],[-48.671,-63.17],[0,0],[0,0]],"o":[[0,0],[28.39,-8.155],[0,0],[0,0]],"v":[[-85.903,-106.746],[69.639,110.528],[100.452,25.753],[-0.506,-106.746]],"c":false}]},{"i":{"x":0.667,"y":1},"o":{"x":0.333,"y":0},"t":70,"s":[{"i":[[0,0],[0,0],[0,0],[0,0]],"o":[[0,0],[0,0],[0,0],[0,0]],"v":[[-85.903,-106.746],[16.213,106.919],[49.085,43.235],[-0.506,-106.746]],"c":false}]},{"i":{"x":0.667,"y":1},"o":{"x":0.333,"y":0},"t":92,"s":[{"i":[[0,0],[0,0],[0,0],[0,0]],"o":[[0,0],[0,0],[0,0],[0,0]],"v":[[-85.903,-106.746],[36.335,107.414],[63.654,38.454],[-0.506,-106.746]],"c":false}]},{"t":117,"s":[{"i":[[0,0],[0,0],[0,0],[0,0]],"o":[[0,0],[0,0],[0,0],[0,0]],"v":[[-85.903,-106.746],[28.256,106.746],[56.615,36.622],[-0.506,-106.746]],"c":false}]}],"ix":2},"nm":"Path 1","mn":"ADBE Vector Shape - Group","hd":false},{"ty":"fl","c":{"a":0,"k":[0.922,0.902,0.937,1],"ix":4,"x":"var $bm_rt;\n$bm_rt = comp('wired-lineal-1780-medal-first-place').layer('control').effect('tertiary')('Color');"},"o":{"a":0,"k":100,"ix":5},"r":1,"bm":0,"nm":".tertiary","mn":"ADBE Vector Graphic - Fill","hd":false,"cl":"tertiary"},{"ty":"tr","p":{"a":0,"k":[206.97,196.627],"ix":2},"a":{"a":0,"k":[0,0],"ix":1},"s":{"a":0,"k":[100,100],"ix":3},"r":{"a":0,"k":0,"ix":6},"o":{"a":0,"k":100,"ix":7},"sk":{"a":0,"k":0,"ix":4},"sa":{"a":0,"k":0,"ix":5},"nm":"Transform"}],"nm":"Group 1","np":2,"cix":2,"bm":0,"ix":1,"mn":"ADBE Vector Group","hd":false},{"ty":"tr","p":{"a":0,"k":[293.03,196.627],"ix":2},"a":{"a":0,"k":[293.03,196.627],"ix":1},"s":{"a":0,"k":[100,100],"ix":3},"r":{"a":0,"k":0,"ix":6},"o":{"a":0,"k":100,"ix":7},"sk":{"a":0,"k":0,"ix":4},"sa":{"a":0,"k":0,"ix":5},"nm":"Transform"}],"nm":"Group 2","np":1,"cix":2,"bm":0,"ix":1,"mn":"ADBE Vector Group","hd":false}],"ip":0,"op":844,"st":0,"ct":1,"bm":1},{"ddd":0,"ind":9,"ty":4,"nm":"Warstwa 1 fill","sr":1,"ks":{"o":{"a":0,"k":100,"ix":11},"r":{"a":0,"k":0,"ix":10},"p":{"a":0,"k":[286.742,147.718,0],"ix":2,"l":2},"a":{"a":0,"k":[0,0,0],"ix":1,"l":2},"s":{"a":0,"k":[100,100,100],"ix":6,"l":2}},"ao":0,"shapes":[{"ty":"gr","it":[{"ind":0,"ty":"sh","ix":1,"ks":{"a":1,"k":[{"i":{"x":0,"y":1},"o":{"x":0.167,"y":0.167},"t":0,"s":[{"i":[[-12.217,-3.055],[0,0],[0,0],[14.385,-36.07]],"o":[[4.783,-11.555],[0,0],[0,0],[3.885,-0.57]],"v":[[-29.026,120.837],[57.128,-92.837],[13.217,-92.956],[-71.628,119.352]],"c":true}]},{"i":{"x":0.833,"y":0.833},"o":{"x":0.333,"y":0},"t":30,"s":[{"i":[[-6.217,-10.055],[0,0],[0,0],[66.885,-51.07]],"o":[[49.783,-46.555],[0,0],[0,0],[7.385,5.93]],"v":[[-106.526,148.837],[57.128,-92.837],[13.217,-92.956],[-142.628,125.852]],"c":true}]},{"i":{"x":0.833,"y":0.833},"o":{"x":0.167,"y":0.167},"t":35,"s":[{"i":[[-12.217,-3.055],[0,0],[0,0],[48.133,-62.03]],"o":[[43.469,-51.797],[0,0],[0,0],[1.885,9.43]],"v":[[-84.962,142.329],[57.128,-92.837],[13.217,-92.956],[-95.051,93.538]],"c":true}]},{"i":{"x":0.833,"y":0.833},"o":{"x":0.167,"y":0.167},"t":38,"s":[{"i":[[-12.217,-3.055],[0,0],[0,0],[37.334,-59.354]],"o":[[31.958,-52.552],[0,0],[0,0],[1.885,9.43]],"v":[[-57.225,133.909],[57.128,-92.837],[13.217,-92.956],[-76.872,92.952]],"c":true}]},{"i":{"x":0.833,"y":0.833},"o":{"x":0.167,"y":0.167},"t":40,"s":[{"i":[[-12.217,-3.055],[0,0],[0,0],[30.135,-57.57]],"o":[[24.283,-53.055],[0,0],[0,0],[1.885,9.43]],"v":[[-35.401,127.462],[57.128,-92.837],[13.217,-92.956],[-62.253,92.977]],"c":true}]},{"i":{"x":0.833,"y":0.833},"o":{"x":0.167,"y":0.167},"t":43,"s":[{"i":[[-12.217,-3.055],[0,0],[0,0],[19.337,-54.894]],"o":[[14.536,-55.54],[0,0],[0,0],[1.885,9.43]],"v":[[-4.914,119.342],[57.128,-92.837],[13.217,-92.956],[-39.19,91.046]],"c":true}]},{"i":{"x":0.833,"y":0.833},"o":{"x":0.167,"y":0.167},"t":45,"s":[{"i":[[-12.217,-3.055],[0,0],[0,0],[12.138,-53.111]],"o":[[8.038,-57.196],[0,0],[0,0],[1.885,9.43]],"v":[[12.911,113.095],[57.128,-92.837],[13.217,-92.956],[-23.814,89.759]],"c":true}]},{"i":{"x":0.667,"y":1},"o":{"x":0.167,"y":0.167},"t":48,"s":[{"i":[[-12.217,-3.055],[0,0],[0,0],[4.474,-51.212]],"o":[[1.12,-58.959],[0,0],[0,0],[1.885,9.43]],"v":[[31.964,108.356],[57.128,-92.837],[13.217,-92.956],[-7.911,88.268]],"c":true}]},{"i":{"x":0.833,"y":0.833},"o":{"x":0.333,"y":0},"t":50,"s":[{"i":[[-12.217,-3.055],[0,0],[0,0],[1.885,-50.57]],"o":[[-1.217,-59.555],[0,0],[0,0],[1.885,9.43]],"v":[[35.724,106.087],[57.128,-92.837],[13.217,-92.956],[-3.878,89.102]],"c":true}]},{"i":{"x":0.833,"y":0.833},"o":{"x":0.167,"y":0.167},"t":53,"s":[{"i":[[-12.217,-3.055],[0,0],[0,0],[4.937,-52.305]],"o":[[2.632,-65.366],[0,0],[0,0],[1.885,9.43]],"v":[[30.563,108.178],[57.128,-92.837],[13.217,-92.956],[-9.003,88.366]],"c":true}]},{"i":{"x":0.833,"y":0.833},"o":{"x":0.167,"y":0.167},"t":56,"s":[{"i":[[-12.217,-3.055],[0,0],[0,0],[10.294,-55.349]],"o":[[9.388,-75.566],[0,0],[0,0],[1.885,9.43]],"v":[[17.369,111.848],[57.128,-92.837],[13.217,-92.956],[-20.755,89.828]],"c":true}]},{"i":{"x":0.833,"y":0.833},"o":{"x":0.167,"y":0.167},"t":60,"s":[{"i":[[-12.217,-3.055],[0,0],[0,0],[19.26,-60.445]],"o":[[19.596,-72.743],[0,0],[0,0],[1.885,9.43]],"v":[[-6.338,119.025],[57.128,-92.837],[13.217,-92.956],[-38.753,90.602]],"c":true}]},{"i":{"x":0.833,"y":0.833},"o":{"x":0.167,"y":0.167},"t":63,"s":[{"i":[[-12.217,-3.055],[0,0],[0,0],[25.755,-64.136]],"o":[[27.817,-72.078],[0,0],[0,0],[1.885,9.43]],"v":[[-24.559,124.86],[57.128,-92.837],[13.217,-92.956],[-51.916,88.91]],"c":true}]},{"i":{"x":0.667,"y":1},"o":{"x":0.167,"y":0.167},"t":66,"s":[{"i":[[-12.217,-3.055],[0,0],[0,0],[32.249,-67.827]],"o":[[36.038,-70.414],[0,0],[0,0],[1.885,9.43]],"v":[[-39.781,128.696],[57.128,-92.837],[13.217,-92.956],[-63.08,91.219]],"c":true}]},{"i":{"x":0.667,"y":1},"o":{"x":0.333,"y":0},"t":70,"s":[{"i":[[-12.217,-3.055],[0,0],[0,0],[36.635,-70.32]],"o":[[35.908,-61.43],[0,0],[0,0],[1.885,9.43]],"v":[[-48.401,131.962],[57.128,-92.837],[13.217,-92.956],[-70.628,94.102]],"c":true}]},{"i":{"x":0.667,"y":1},"o":{"x":0.333,"y":0},"t":92,"s":[{"i":[[-12.217,-3.055],[0,0],[0,0],[26.885,-68.57]],"o":[[25.658,-64.18],[0,0],[0,0],[1.885,9.43]],"v":[[-24.401,123.712],[57.128,-92.837],[13.217,-92.956],[-52.378,91.602]],"c":true}]},{"t":117,"s":[{"i":[[-12.217,-3.055],[0,0],[0,0],[26.885,-68.57]],"o":[[25.658,-64.18],[0,0],[0,0],[1.885,9.43]],"v":[[-29.151,119.962],[57.128,-92.837],[13.217,-92.956],[-55.628,78.352]],"c":true}]}],"ix":2},"nm":"Path 1","mn":"ADBE Vector Shape - Group","hd":false},{"ty":"fl","c":{"a":0,"k":[0.443,0.4,0.933,1],"ix":4,"x":"var $bm_rt;\n$bm_rt = comp('wired-lineal-1780-medal-first-place').layer('control').effect('quaternary')('Color');"},"o":{"a":0,"k":100,"ix":5},"r":1,"bm":0,"nm":".quaternary","mn":"ADBE Vector Graphic - Fill","hd":false,"cl":"quaternary"},{"ty":"tr","p":{"a":0,"k":[0,0],"ix":2},"a":{"a":0,"k":[0,0],"ix":1},"s":{"a":0,"k":[100,100],"ix":3},"r":{"a":0,"k":0,"ix":6},"o":{"a":0,"k":100,"ix":7},"sk":{"a":0,"k":0,"ix":4},"sa":{"a":0,"k":0,"ix":5},"nm":"Transform"}],"nm":"Group 1","np":2,"cix":2,"bm":0,"ix":1,"mn":"ADBE Vector Group","hd":false}],"ip":0,"op":844,"st":0,"ct":1,"bm":0},{"ddd":0,"ind":10,"ty":4,"nm":"Ribbon 4 fill","sr":1,"ks":{"o":{"a":0,"k":100,"ix":11},"r":{"a":0,"k":0,"ix":10},"p":{"a":0,"k":[215,161.627,0],"ix":2,"l":2},"a":{"a":0,"k":[250,196.627,0],"ix":1,"l":2},"s":{"a":0,"k":[100,100,100],"ix":6,"l":2}},"ao":0,"shapes":[{"ty":"gr","it":[{"ty":"gr","it":[{"ind":0,"ty":"sh","ix":1,"ks":{"a":1,"k":[{"i":{"x":0.015,"y":1},"o":{"x":0.167,"y":0.167},"t":0,"s":[{"i":[[0,0],[26.976,-68.373],[0,0],[0,0]],"o":[[0,0],[-33.524,0.127],[0,0],[0,0]],"v":[[85.903,-106.746],[-0.506,106.746],[-85.903,106.746],[0.506,-106.746]],"c":false}]},{"i":{"x":0.667,"y":1},"o":{"x":0.333,"y":0},"t":30,"s":[{"i":[[0,0],[55.825,-52.422],[18.787,11.765],[0,0]],"o":[[0,0],[-28.513,-17.631],[64.287,-55.735],[0,0]],"v":[[85.903,-106.746],[-78.855,135.295],[-151.317,90.108],[0.506,-106.746]],"c":false}]},{"i":{"x":0.667,"y":1},"o":{"x":0.333,"y":0},"t":50,"s":[{"i":[[0,0],[1.994,-81.852],[0,0],[0,0]],"o":[[0,0],[-31.868,10.408],[0,0],[0,0]],"v":[[85.903,-106.746],[64.538,92.47],[-16.752,118.635],[0.506,-106.746]],"c":false}]},{"i":{"x":0.667,"y":1},"o":{"x":0.333,"y":0},"t":70,"s":[{"i":[[0,0],[35.568,-59.435],[0,0],[0,0]],"o":[[0,0],[-29.895,-6.086],[0,0],[0,0]],"v":[[85.903,-106.746],[-19.811,117.661],[-95.908,101.854],[0.506,-106.746]],"c":false}]},{"i":{"x":0.667,"y":1},"o":{"x":0.333,"y":0},"t":92,"s":[{"i":[[0,0],[25.975,-65.84],[0,0],[0,0]],"o":[[0,0],[-30.458,-1.373],[0,0],[0,0]],"v":[[85.903,-106.746],[4.289,110.464],[-73.292,106.649],[0.506,-106.746]],"c":false}]},{"t":117,"s":[{"i":[[0,0],[26.976,-68.373],[0,0],[0,0]],"o":[[0,0],[-33.524,0.127],[0,0],[0,0]],"v":[[85.903,-106.746],[-0.506,106.746],[-85.903,106.746],[0.506,-106.746]],"c":false}]}],"ix":2},"nm":"Path 1","mn":"ADBE Vector Shape - Group","hd":false},{"ty":"fl","c":{"a":0,"k":[0.922,0.902,0.937,1],"ix":4,"x":"var $bm_rt;\n$bm_rt = comp('wired-lineal-1780-medal-first-place').layer('control').effect('tertiary')('Color');"},"o":{"a":0,"k":100,"ix":5},"r":1,"bm":0,"nm":".tertiary","mn":"ADBE Vector Graphic - Fill","hd":false,"cl":"tertiary"},{"ty":"tr","p":{"a":0,"k":[293.03,196.627],"ix":2},"a":{"a":0,"k":[0,0],"ix":1},"s":{"a":0,"k":[100,100],"ix":3},"r":{"a":0,"k":0,"ix":6},"o":{"a":0,"k":100,"ix":7},"sk":{"a":0,"k":0,"ix":4},"sa":{"a":0,"k":0,"ix":5},"nm":"Transform"}],"nm":"Group 2","np":2,"cix":2,"bm":0,"ix":1,"mn":"ADBE Vector Group","hd":false},{"ty":"tr","p":{"a":0,"k":[293.03,196.627],"ix":2},"a":{"a":0,"k":[293.03,196.627],"ix":1},"s":{"a":0,"k":[100,100],"ix":3},"r":{"a":0,"k":0,"ix":6},"o":{"a":0,"k":100,"ix":7},"sk":{"a":0,"k":0,"ix":4},"sa":{"a":0,"k":0,"ix":5},"nm":"Transform"}],"nm":"Group 2","np":1,"cix":2,"bm":0,"ix":1,"mn":"ADBE Vector Group","hd":false}],"ip":0,"op":844,"st":0,"ct":1,"bm":0}]}],"layers":[{"ddd":0,"ind":1,"ty":3,"nm":"control","sr":1,"ks":{"o":{"a":0,"k":0,"ix":11},"r":{"a":0,"k":0,"ix":10},"p":{"a":0,"k":[0,0],"ix":2,"l":2},"a":{"a":0,"k":[0,0,0],"ix":1,"l":2},"s":{"a":0,"k":[100,100,100],"ix":6,"l":2}},"ao":0,"ef":[{"ty":5,"nm":"stroke","np":3,"mn":"Pseudo/@@gm+ERwKKQM26+MAN3m7Dnw","ix":1,"en":1,"ef":[{"ty":7,"nm":"Menu","mn":"Pseudo/@@gm+ERwKKQM26+MAN3m7Dnw-0001","ix":1,"v":{"a":0,"k":2,"ix":1}}]},{"ty":5,"nm":"primary","np":3,"mn":"ADBE Color Control","ix":2,"en":1,"ef":[{"ty":2,"nm":"Color","mn":"ADBE Color Control-0001","ix":1,"v":{"a":0,"k":[0.071,0.075,0.192],"ix":1}}]},{"ty":5,"nm":"secondary","np":3,"mn":"ADBE Color Control","ix":3,"en":1,"ef":[{"ty":2,"nm":"Color","mn":"ADBE Color Control-0001","ix":1,"v":{"a":0,"k":[1,0.78,0.22],"ix":1}}]},{"ty":5,"nm":"tertiary","np":3,"mn":"ADBE Color Control","ix":4,"en":1,"ef":[{"ty":2,"nm":"Color","mn":"ADBE Color Control-0001","ix":1,"v":{"a":0,"k":[0.922,0.902,0.937],"ix":1}}]},{"ty":5,"nm":"quaternary","np":3,"mn":"ADBE Color Control","ix":5,"en":1,"ef":[{"ty":2,"nm":"Color","mn":"ADBE Color Control-0001","ix":1,"v":{"a":0,"k":[0.443,0.4,0.933],"ix":1}}]},{"ty":5,"nm":"quinary","np":3,"mn":"ADBE Color Control","ix":6,"en":1,"ef":[{"ty":2,"nm":"Color","mn":"ADBE Color Control-0001","ix":1,"v":{"a":0,"k":[0.698,0.408,0.212],"ix":1}}]}],"ip":0,"op":225,"st":0,"bm":0},{"ddd":0,"ind":3,"ty":0,"nm":"hover-pinch","refId":"comp_2","sr":1,"ks":{"o":{"a":0,"k":100,"ix":11},"r":{"a":0,"k":0,"ix":10},"p":{"a":0,"k":[215,215,0],"ix":2,"l":2},"a":{"a":0,"k":[215,215,0],"ix":1,"l":2},"s":{"a":0,"k":[100,100,100],"ix":6,"l":2}},"ao":0,"w":430,"h":430,"ip":0,"op":134,"st":0,"bm":0}],"markers":[{"tm":0,"cm":"default:hover-pinch","dr":124}],"props":{}}